{"1": {"url": "https://www.jstage.jst.go.jp/article/pjsai/JSAI03/0/JSAI03_0_1/_article/-char/ja", "title": "アートからデザインへの転換について -音楽情報処理の事例から-", "keywords": [], "co-author": [], "org": {"NTT": 1, "コミュニケーション科学基礎研究所": 2}, "author_org": {"1": ["平田 圭二"], "2": ["平田 圭二"]}, "author": "平田 圭二", "abstract": null}, "2": {"url": "https://www.jstage.jst.go.jp/article/pjsai/JSAI03/0/JSAI03_0_2/_article/-char/ja", "title": "計算機による演奏はどのように評価され得るか", "keywords": [], "co-author": ["片寄 晴弘", "平田 圭二"], "org": {"文教大学": 1, "関西学院大学・さきがけ研究21": 2, "NTTコミュニケーション科学研究所": 3}, "author_org": {"1": ["平賀 瑠美"], "2": ["片寄 晴弘"], "3": ["平田 圭二"]}, "author": "平賀 瑠美", "abstract": null}, "3": {"url": "https://www.jstage.jst.go.jp/article/pjsai/JSAI03/0/JSAI03_0_3/_article/-char/ja", "title": "名演奏を下敷に演奏表現を行うシステム punin：データ表現とコントローラ", "keywords": [], "co-author": ["野池 賢二", "橋田 光代", "奥平 啓太"], "org": {"関西学院大学理工学部情報科学科": 1, "科技団さきがけ研究２１": 2}, "author_org": {"1": ["片寄 晴弘", "奥平 啓太"], "2": ["片寄 晴弘", "野池 賢二", "橋田 光代"]}, "author": "片寄 晴弘", "abstract": null}, "4": {"url": "https://www.jstage.jst.go.jp/article/pjsai/JSAI03/0/JSAI03_0_4/_article/-char/ja", "title": "SIC (Synergistic Image Creator)を新たな絵筆にするために必要な研究要素", "keywords": [], "co-author": [], "org": {"東京工芸大学": 1, "ATR": 2}, "author_org": {"1": ["笠尾 敦司"], "2": ["笠尾 敦司"]}, "author": "笠尾 敦司", "abstract": null}, "5": {"url": "https://www.jstage.jst.go.jp/article/pjsai/JSAI03/0/JSAI03_0_5/_article/-char/ja", "title": "階層的筆触データを用いた絵画表現の一手法", "keywords": [], "co-author": ["笠尾 敦司", "蓼沼 眞"], "org": {"北陸先端科学技術大学院大学": 1, "東京工芸大学": 2, "（株）ＡＴＲ": 3}, "author_org": {"1": ["宮田 一乘"], "2": ["笠尾 敦司"], "3": ["蓼沼 眞"]}, "author": "宮田 一乘", "abstract": null}, "6": {"url": "https://www.jstage.jst.go.jp/article/pjsai/JSAI03/0/JSAI03_0_6/_article/-char/ja", "title": "事例に基づくキャラクターデザイン支援に関する研究　─曲率半径と周波数分析を用いた顔の曲面を構成する曲線の特徴抽出", "keywords": [], "co-author": ["原田 利宣", "片寄 晴弘"], "org": {"和歌山大学": 1, "関西学院大学": 2}, "author_org": {"1": ["山田 浩子", "原田 利宣"], "2": ["片寄 晴弘"]}, "author": "山田 浩子", "abstract": null}, "7": {"url": "https://www.jstage.jst.go.jp/article/pjsai/JSAI03/0/JSAI03_0_7/_article/-char/ja", "title": "モーションデザインの再利用によるアニメーション作成支援", "keywords": [], "co-author": [], "org": {"筑波大学": 1}, "author_org": {"1": ["星野 准一"]}, "author": "星野 准一", "abstract": null}, "8": {"url": "https://www.jstage.jst.go.jp/article/pjsai/JSAI03/0/JSAI03_0_8/_article/-char/ja", "title": "アニメーションキャラクタの体型を考慮した同化動作生成手法", "keywords": [], "co-author": ["原口 誠"], "org": {"北海道大学大学院工学研究科電子情報工学専攻": 1}, "author_org": {"1": ["本林 正裕", "原口 誠"]}, "author": "本林 正裕", "abstract": null}, "9": {"url": "https://www.jstage.jst.go.jp/article/pjsai/JSAI03/0/JSAI03_0_9/_article/-char/ja", "title": "ストーリー型インタラクティブシステム構築基盤", "keywords": [], "co-author": [], "org": {"筑波大学機能工学系": 1}, "author_org": {"1": ["星野 准一"]}, "author": "星野 准一", "abstract": null}, "10": {"url": "https://www.jstage.jst.go.jp/article/pjsai/JSAI03/0/JSAI03_0_10/_article/-char/ja", "title": "身体化された音声インタラクション", "keywords": [], "co-author": [], "org": {"公立はこだて未来大学": 1, "ＡＴＲ知能ロボティクス研究所": 2}, "author_org": {"1": ["小野 哲雄"], "2": ["小野 哲雄"]}, "author": "小野 哲雄", "abstract": null}, "11": {"url": "https://www.jstage.jst.go.jp/article/pjsai/JSAI03/0/JSAI03_0_11/_article/-char/ja", "title": "分子ミュージック：分子が奏でる音を聴く", "keywords": [], "co-author": ["高橋 由雅"], "org": {"豊橋技術科学大学　工学部": 1}, "author_org": {"1": ["冨士本 貴行", "高橋 由雅"]}, "author": "冨士本 貴行", "abstract": null}, "12": {"url": "https://www.jstage.jst.go.jp/article/pjsai/JSAI03/0/JSAI03_0_12/_article/-char/ja", "title": "インタラクティブ作曲支援システム_から_ユーザの負担の軽減_から_", "keywords": [], "co-author": ["鬼沢 武久"], "org": {"筑波大学システム情報工学研究科": 1, "筑波大学機能工学系": 2}, "author_org": {"1": ["畦原 宗之"], "2": ["鬼沢 武久"]}, "author": "畦原 宗之", "abstract": null}, "13": {"url": "https://www.jstage.jst.go.jp/article/pjsai/JSAI03/0/JSAI03_0_13/_article/-char/ja", "title": "大都市大震災軽減化特別プロジェクトにおける震災総合シミュレーションシステムアーキテクチャ", "keywords": [], "co-author": ["野田 五十樹", "桑田 喜隆", "竹内 郁雄"], "org": {"電気通信大学": 1, "産業技術総合研究所": 2, "NTTデータ": 3}, "author_org": {"1": ["小藤 哲彦", "竹内 郁雄"], "2": ["小藤 哲彦", "野田 五十樹"], "3": ["桑田 喜隆"]}, "author": "小藤 哲彦", "abstract": null}, "14": {"url": "https://www.jstage.jst.go.jp/article/pjsai/JSAI03/0/JSAI03_0_14/_article/-char/ja", "title": "災害救助リスクコミュニケーションおける市民エージェントの役割とその作成", "keywords": [], "co-author": ["野田 五十樹"], "org": {"産総研": 1, "サイバーアシスト研究センタ": 2, "北陸先端科学技術大学院大学": 3, "さきがけ研究21": 4}, "author_org": {"1": ["篠田 孝祐", "野田 五十樹"], "2": ["篠田 孝祐", "野田 五十樹"], "3": ["篠田 孝祐", "野田 五十樹"], "4": ["野田 五十樹"]}, "author": "篠田 孝祐", "abstract": null}, "15": {"url": "https://www.jstage.jst.go.jp/article/pjsai/JSAI03/0/JSAI03_0_15/_article/-char/ja", "title": "災害救助における燃焼家屋クラスタリングの一考察", "keywords": [], "co-author": ["伊藤 暢浩", "犬塚 信博", "和田 幸一"], "org": {"名古屋工業大学電気情報工学科": 1}, "author_org": {"1": ["本地 健一", "伊藤 暢浩", "犬塚 信博", "和田 幸一"]}, "author": "本地 健一", "abstract": null}, "16": {"url": "https://www.jstage.jst.go.jp/article/pjsai/JSAI03/0/JSAI03_0_16/_article/-char/ja", "title": "災害情報視覚化のためのビューワ間通信プロトコル", "keywords": [], "co-author": ["神成 淳司", "竹内 郁雄", "野田 五十樹"], "org": {"NTTデータ": 1, "国際情報科学芸術アカデミー": 2, "電気通信大学": 3, "産業技術総合研究所": 4}, "author_org": {"1": ["桑田 喜隆"], "2": ["神成 淳司"], "3": ["竹内 郁雄"], "4": ["野田 五十樹"]}, "author": "桑田 喜隆", "abstract": null}, "17": {"url": "https://www.jstage.jst.go.jp/article/pjsai/JSAI03/0/JSAI03_0_17/_article/-char/ja", "title": "視覚センサネットワークを用いた避難シミュレータとその実験構想", "keywords": [], "co-author": ["中西 英之", "石黒 浩", "石田 亨"], "org": {"科学技術振興事業団CREST": 1, "京都大学大学院情報学研究科": 2, "大阪大学大学院工学研究科": 3}, "author_org": {"1": ["小泉 智史"], "2": ["中西 英之", "石田 亨"], "3": ["石黒 浩"]}, "author": "小泉 智史", "abstract": null}, "18": {"url": "https://www.jstage.jst.go.jp/article/pjsai/JSAI03/0/JSAI03_0_18/_article/-char/ja", "title": "Webナビゲーションのためのブラウジングパターンの学習", "keywords": [], "co-author": ["山田 誠二"], "org": {"東京工業大学大学院　総合理工学研究科　知能システム科学専攻": 1, "国立情報学研究所": 2}, "author_org": {"1": ["梛野 憲克"], "2": ["山田 誠二"]}, "author": "梛野 憲克", "abstract": null}, "19": {"url": "https://www.jstage.jst.go.jp/article/pjsai/JSAI03/0/JSAI03_0_19/_article/-char/ja", "title": "ユーザ感情を考慮したインタフェースエージェントの行動決定", "keywords": [], "co-author": [], "org": {"東京大学": 1}, "author_org": {"1": ["森 純一郎"]}, "author": "森 純一郎", "abstract": null}, "20": {"url": "https://www.jstage.jst.go.jp/article/pjsai/JSAI03/0/JSAI03_0_20/_article/-char/ja", "title": "日常的なインタラクションによるユーザエージェントの実現", "keywords": [], "co-author": ["礒田 佳徳", "長沼 武史", "倉掛 正治"], "org": {"NTTドコモ　マルチメディア研究所": 1}, "author_org": {"1": ["黒宮 寧", "礒田 佳徳", "長沼 武史", "倉掛 正治"]}, "author": "黒宮 寧", "abstract": null}, "21": {"url": "https://www.jstage.jst.go.jp/article/pjsai/JSAI03/0/JSAI03_0_21/_article/-char/ja", "title": "確率的推論を利用したマルチモーダル対話制御", "keywords": [], "co-author": ["小玉 智志", "KHIAT ABDELAZIZ", "松本 泰明", "本村 陽一", "原 功", "浅野 太", "小笠原 司", "新田 恒雄", "柿倉 正義"], "org": {"産業技術総合研究所": 1, "豊橋技術科学大学": 2, "奈良先端科学技術大学院大学": 3, "東京電機大学": 4}, "author_org": {"1": ["麻生 英樹", "本村 陽一", "原 功", "浅野 太"], "2": ["小玉 智志", "新田 恒雄"], "3": ["KHIAT ABDELAZIZ", "小笠原 司"], "4": ["松本 泰明", "柿倉 正義"]}, "author": "麻生 英樹", "abstract": null}, "22": {"url": "https://www.jstage.jst.go.jp/article/pjsai/JSAI03/0/JSAI03_0_22/_article/-char/ja", "title": "対話文脈への入力文の意味の位置付け手法", "keywords": [], "co-author": ["池ヶ谷 有希", "鈴木 夕紀子", "伊藤 敏彦", "小西 達裕", "近藤 真", "高木 朗", "中島 秀之", "伊東 幸宏"], "org": {"静岡大学情報学部": 1, "（株）CSK": 2, "産総研サイバーアシスト研究センター": 3}, "author_org": {"1": ["野口 靖浩", "池ヶ谷 有希", "鈴木 夕紀子", "伊藤 敏彦", "小西 達裕", "近藤 真", "伊東 幸宏"], "2": ["高木 朗"], "3": ["高木 朗", "中島 秀之"]}, "author": "野口 靖浩", "abstract": null}, "23": {"url": "https://www.jstage.jst.go.jp/article/pjsai/JSAI03/0/JSAI03_0_23/_article/-char/ja", "title": "音響情報を利用した言い直しの検出", "keywords": [], "co-author": ["鈴木 泰裕", "徳永 健伸", "田中 穂積"], "org": {"東京工業大学": 1}, "author_org": {"1": ["船越 孝太郎", "鈴木 泰裕", "徳永 健伸", "田中 穂積"]}, "author": "船越 孝太郎", "abstract": null}, "24": {"url": "https://www.jstage.jst.go.jp/article/pjsai/JSAI03/0/JSAI03_0_24/_article/-char/ja", "title": "視覚的類似性に基づくwebページ検索手法の提案", "keywords": [], "co-author": ["山口 亨", "高間 康史"], "org": {"都立科学技術大学": 1, "科学技術振興事業団": 2}, "author_org": {"1": ["三橋 憲晃", "山口 亨", "高間 康史"], "2": ["山口 亨", "高間 康史"]}, "author": "三橋 憲晃", "abstract": null}, "25": {"url": "https://www.jstage.jst.go.jp/article/pjsai/JSAI03/0/JSAI03_0_25/_article/-char/ja", "title": "Web上の表検索", "keywords": [], "co-author": ["廣川 佐千男"], "org": {"九州大学": 1}, "author_org": {"1": ["野口 正人", "廣川 佐千男"]}, "author": "野口 正人", "abstract": null}, "26": {"url": "https://www.jstage.jst.go.jp/article/pjsai/JSAI03/0/JSAI03_0_26/_article/-char/ja", "title": "文書ベクトル列の複合汎化を用いた物語性に基づく文書検索", "keywords": [], "co-author": ["小木曽 聡"], "org": {"北海道大学工学研究科": 1}, "author_org": {"1": ["小木曽 聡", "山本 章博"]}, "author": "山本 章博", "abstract": null}, "27": {"url": "https://www.jstage.jst.go.jp/article/pjsai/JSAI03/0/JSAI03_0_27/_article/-char/ja", "title": "類似概念判別に基づく情報検索システムの検索性能の評価", "keywords": [], "co-author": ["湯川 高志"], "org": {"長岡技術科学大学": 1}, "author_org": {"1": ["阿部 仁志", "湯川 高志"]}, "author": "阿部 仁志", "abstract": null}, "28": {"url": "https://www.jstage.jst.go.jp/article/pjsai/JSAI03/0/JSAI03_0_28/_article/-char/ja", "title": "対話文を用いた語の関連性の構築手法の提案", "keywords": [], "co-author": ["榑松 理樹", "藤田 ハミド"], "org": {"岩手県立大学": 1}, "author_org": {"1": ["古田 陽", "榑松 理樹", "藤田 ハミド"]}, "author": "古田 陽", "abstract": null}, "29": {"url": "https://www.jstage.jst.go.jp/article/pjsai/JSAI03/0/JSAI03_0_29/_article/-char/ja", "title": "概念共起辞書を用いた文書種類によるクラスタリング", "keywords": [], "co-author": ["石塚 満"], "org": {"東京大学大学院情報理工学系研究科": 1}, "author_org": {"1": ["友部 博教", "石塚 満"]}, "author": "友部 博教", "abstract": null}, "30": {"url": "https://www.jstage.jst.go.jp/article/pjsai/JSAI03/0/JSAI03_0_30/_article/-char/ja", "title": "シソーラスによる多次元空間への単語配置の補正", "keywords": [], "co-author": [], "org": {"日本電信電話株式会社": 1, "NTTコミュニケーション科学基礎研究所": 2}, "author_org": {"1": ["笠原 要"], "2": ["笠原 要"]}, "author": "笠原 要", "abstract": null}, "31": {"url": "https://www.jstage.jst.go.jp/article/pjsai/JSAI03/0/JSAI03_0_31/_article/-char/ja", "title": "Support Vector Machineを用いた未知語の検出", "keywords": [], "co-author": ["石塚 満"], "org": {"東京大学大学院": 1, "情報理工学系研究科": 2, "電子情報学専攻": 3}, "author_org": {"1": ["倉田 岳人", "石塚 満"], "2": ["倉田 岳人", "石塚 満"], "3": ["倉田 岳人", "石塚 満"]}, "author": "倉田 岳人", "abstract": null}, "32": {"url": "https://www.jstage.jst.go.jp/article/pjsai/JSAI03/0/JSAI03_0_32/_article/-char/ja", "title": "発信者情報が付与されたテキストコーパスの分析について", "keywords": [], "co-author": [], "org": {"国立情報学研究所": 1}, "author_org": {"1": ["相澤 彰子"]}, "author": "相澤 彰子", "abstract": null}, "33": {"url": "https://www.jstage.jst.go.jp/article/pjsai/JSAI03/0/JSAI03_0_33/_article/-char/ja", "title": "コンテンツネットワークを考慮した文書要約", "keywords": [], "co-author": [""], "org": {"東京大学情報理工学系研究科電子情報学専攻": 1, "著者所属：産業総合研究所サイバーアシストセンター": 2}, "author_org": {"1": ["綾 聡平"], "2": [""]}, "author": "綾 聡平", "abstract": null}, "34": {"url": "https://www.jstage.jst.go.jp/article/pjsai/JSAI03/0/JSAI03_0_34/_article/-char/ja", "title": "演出を用いた実世界情報の顕在化の研究", "keywords": [], "co-author": ["今井 倫太"], "org": {"慶應義塾大学　理工学部": 1, "科学技術振興事業団　さきがけ研究21": 2}, "author_org": {"1": ["鳴海 真里子", "今井 倫太"], "2": ["今井 倫太"]}, "author": "鳴海 真里子", "abstract": null}, "35": {"url": "https://www.jstage.jst.go.jp/article/pjsai/JSAI03/0/JSAI03_0_35/_article/-char/ja", "title": "人間と小型移動ロボットによる協調掃引", "keywords": [], "co-author": ["山田 誠二"], "org": {"総合研究大学院大学": 1, "国立情報学研究所": 2}, "author_org": {"1": ["小林 一樹", "山田 誠二"], "2": ["山田 誠二"]}, "author": "小林 一樹", "abstract": null}, "36": {"url": "https://www.jstage.jst.go.jp/article/pjsai/JSAI03/0/JSAI03_0_36/_article/-char/ja", "title": "対話型進化ロボティクスにおける教示のタイミング", "keywords": [], "co-author": ["山田 誠二"], "org": {"東京工業大学": 1, "国立情報学研究所": 2}, "author_org": {"1": ["片上 大輔"], "2": ["山田 誠二"]}, "author": "片上 大輔", "abstract": null}, "37": {"url": "https://www.jstage.jst.go.jp/article/pjsai/JSAI03/0/JSAI03_0_37/_article/-char/ja", "title": "人間とロボットの感情的インタラクション", "keywords": [], "co-author": ["西田 豊明"], "org": {"東京大学大学院情報理工学系研究科電子情報学専攻": 1}, "author_org": {"1": ["田島 敬士", "西田 豊明"]}, "author": "田島 敬士", "abstract": null}, "38": {"url": "https://www.jstage.jst.go.jp/article/pjsai/JSAI03/0/JSAI03_0_38/_article/-char/ja", "title": "同調動作に基づくロボットと人間のコミュニケーション", "keywords": [], "co-author": ["西田 豊明"], "org": {"東京大学大学院情報理工学系研究科": 1}, "author_org": {"1": ["畠山 誠", "西田 豊明"]}, "author": "畠山 誠", "abstract": null}, "39": {"url": "https://www.jstage.jst.go.jp/article/pjsai/JSAI03/0/JSAI03_0_39/_article/-char/ja", "title": "ロボットと人とのコミュニケーションの誘進的確立", "keywords": [], "co-author": ["畠山 誠", "西田 豊明"], "org": {"東京大学大学院情報理工学系研究科": 1}, "author_org": {"1": ["畑田 寛久", "畠山 誠", "西田 豊明"]}, "author": "畑田 寛久", "abstract": null}, "40": {"url": "https://www.jstage.jst.go.jp/article/pjsai/JSAI03/0/JSAI03_0_40/_article/-char/ja", "title": "状況と文脈に基づいて発話を解釈するサービスロボット用対話システム", "keywords": [], "co-author": ["槙原 靖", "島田 伸敬", "白井 良明"], "org": {"大阪大学大学院工学研究科電子制御機械工学専攻": 1}, "author_org": {"1": ["滝澤 正夫", "槙原 靖", "島田 伸敬", "白井 良明"]}, "author": "滝澤 正夫", "abstract": null}, "41": {"url": "https://www.jstage.jst.go.jp/article/pjsai/JSAI03/0/JSAI03_0_41/_article/-char/ja", "title": "セマンティクス導入によるユーザ指向Webサービス連携支援", "keywords": [], "co-author": ["村上 陽平", "荒井 幸代", "石田 亨"], "org": {"京都大学大学院情報学研究科社会情報学専攻": 1}, "author_org": {"1": ["杉本 悠樹", "村上 陽平", "荒井 幸代", "石田 亨"]}, "author": "杉本 悠樹", "abstract": null}, "42": {"url": "https://www.jstage.jst.go.jp/article/pjsai/JSAI03/0/JSAI03_0_42/_article/-char/ja", "title": "「ユーザ管理からみたWebサービスの現状と実現可能性」", "keywords": [], "co-author": [], "org": {"NTT": 1}, "author_org": {"1": ["藤崎 恵美子"]}, "author": "藤崎 恵美子", "abstract": null}, "43": {"url": "https://www.jstage.jst.go.jp/article/pjsai/JSAI03/0/JSAI03_0_43/_article/-char/ja", "title": "MOP3：セマンティックウェブプロセッサ", "keywords": [], "co-author": ["北村 幸雄"], "org": {"ギャラクシーエクスプレス株式会社": 1}, "author_org": {"1": ["小出 誠二", "北村 幸雄"]}, "author": "小出 誠二", "abstract": null}, "44": {"url": "https://www.jstage.jst.go.jp/article/pjsai/JSAI03/0/JSAI03_0_44/_article/-char/ja", "title": "ユーザオントロジーに基づく適応的リソース選択のためのフレームワークの実現", "keywords": [], "co-author": ["門林 理恵子"], "org": {"通信総合研究所": 1}, "author_org": {"1": ["官上 大輔", "門林 理恵子"]}, "author": "官上 大輔", "abstract": null}, "45": {"url": "https://www.jstage.jst.go.jp/article/pjsai/JSAI03/0/JSAI03_0_45/_article/-char/ja", "title": "有効な組み合わせの発見による創造活動支援", "keywords": [], "co-author": ["砂山 渡", "谷内田 正彦"], "org": {"大阪大学大学院基礎工学研究科": 1}, "author_org": {"1": ["西原 陽子", "砂山 渡", "谷内田 正彦"]}, "author": "西原 陽子", "abstract": null}, "46": {"url": "https://www.jstage.jst.go.jp/article/pjsai/JSAI03/0/JSAI03_0_46/_article/-char/ja", "title": "Webページ集合からの階層的知識の構築", "keywords": [], "co-author": ["山田 誠二"], "org": {"東京工業大学": 1, "大学院": 2, "総合理工学研究科": 3, "知能システム専攻": 4, "国立情報学研究所": 5}, "author_org": {"1": ["間瀬 心博"], "2": ["間瀬 心博"], "3": ["間瀬 心博"], "4": ["間瀬 心博"], "5": ["山田 誠二"]}, "author": "間瀬 心博", "abstract": null}, "47": {"url": "https://www.jstage.jst.go.jp/article/pjsai/JSAI03/0/JSAI03_0_47/_article/-char/ja", "title": "階層的知識と内容的類似性を用いたインターネットディレクトリの統合", "keywords": [], "co-author": ["武田 英明", "市瀬 龍太郎"], "org": {"国立情報学研究所": 1, "総合研究大学院大学": 2}, "author_org": {"1": ["濱崎 雅弘", "武田 英明", "市瀬 龍太郎"], "2": ["濱崎 雅弘", "武田 英明", "市瀬 龍太郎"]}, "author": "濱崎 雅弘", "abstract": null}, "48": {"url": "https://www.jstage.jst.go.jp/article/pjsai/JSAI03/0/JSAI03_0_48/_article/-char/ja", "title": "WebシラバスからのDB構成", "keywords": [], "co-author": ["松永 吉広", "山田 信太郎", "廣川 佐千男"], "org": {"九州大学": 1}, "author_org": {"1": ["伊東 栄典", "松永 吉広", "山田 信太郎", "廣川 佐千男"]}, "author": "伊東 栄典", "abstract": null}, "49": {"url": "https://www.jstage.jst.go.jp/article/pjsai/JSAI03/0/JSAI03_0_49/_article/-char/ja", "title": "XMLデータストリームからの高速な知識発見手法", "keywords": [], "co-author": ["安部 賢治", "川副 真治", "有村 博紀", "有川 節夫"], "org": {"九州大学": 1, "大学院システム情報科学府・研究院": 2}, "author_org": {"1": ["浅井 達哉", "安部 賢治", "川副 真治", "有村 博紀", "有川 節夫"], "2": ["浅井 達哉", "安部 賢治", "川副 真治", "有村 博紀", "有川 節夫"]}, "author": "浅井 達哉", "abstract": null}, "57": {"url": "https://www.jstage.jst.go.jp/article/pjsai/JSAI03/0/JSAI03_0_57/_article/-char/ja", "title": "キャンプ環境における児童によるパブリック・オピニオン・チャンネルの使用報告", "keywords": [], "co-author": ["福原 知宏", "西田 豊明"], "org": {"通信総合研究所": 1, "東京大学": 2}, "author_org": {"1": ["山下 耕二", "福原 知宏"], "2": ["西田 豊明"]}, "author": "山下 耕二", "abstract": null}, "58": {"url": "https://www.jstage.jst.go.jp/article/pjsai/JSAI03/0/JSAI03_0_58/_article/-char/ja", "title": "Collaborative Question-Answering System for e-Learning", "keywords": [], "co-author": ["石川 孝"], "org": {"日本工業大学": 1}, "author_org": {"1": ["ウォンウィブンシン タナチャイ", "石川 孝"]}, "author": "ウォンウィブンシン タナチャイ", "abstract": null}, "59": {"url": "https://www.jstage.jst.go.jp/article/pjsai/JSAI03/0/JSAI03_0_59/_article/-char/ja", "title": "事例を用いた模擬裁判支援システム", "keywords": [], "co-author": ["西原 国義", "安村 禎明", "新田 克己"], "org": {"東京工業大学": 1}, "author_org": {"1": ["田中 貴絋", "西原 国義", "安村 禎明", "新田 克己"]}, "author": "田中 貴絋", "abstract": null}, "60": {"url": "https://www.jstage.jst.go.jp/article/pjsai/JSAI03/0/JSAI03_0_60/_article/-char/ja", "title": "指導案オーサリングシステムTeaPoTについて", "keywords": [], "co-author": [], "org": {"滋賀大学教育学部": 1}, "author_org": {"1": ["岩井 憲一"]}, "author": "岩井 憲一", "abstract": null}, "61": {"url": "https://www.jstage.jst.go.jp/article/pjsai/JSAI03/0/JSAI03_0_61/_article/-char/ja", "title": "自閉症児を対象としたデジタルコンテンツ作成支援システムの設計", "keywords": [], "co-author": [], "org": {"和歌山大学システム工学部": 1}, "author_org": {"1": ["小川 修史"]}, "author": "小川 修史", "abstract": null}, "62": {"url": "https://www.jstage.jst.go.jp/article/pjsai/JSAI03/0/JSAI03_0_62/_article/-char/ja", "title": "問題間の関係の外化を支援する知的学習支援環境", "keywords": [], "co-author": [], "org": {"九州工業大学": 1}, "author_org": {"1": ["中野 明"]}, "author": "中野 明", "abstract": null}, "63": {"url": "https://www.jstage.jst.go.jp/article/pjsai/JSAI03/0/JSAI03_0_63/_article/-char/ja", "title": "学習者の生理状態をフィードバックする学習支援環境", "keywords": [], "co-author": ["清水 友明", "田村 恭久"], "org": {"上智大学": 1}, "author_org": {"1": ["田村 芳明", "清水 友明", "田村 恭久"]}, "author": "田村 芳明", "abstract": null}, "64": {"url": "https://www.jstage.jst.go.jp/article/pjsai/JSAI03/0/JSAI03_0_64/_article/-char/ja", "title": "学習者の自律性を考慮したe-Learning環境のデザインに向けて", "keywords": [], "co-author": [], "org": {"青山学院大学文学研究科教育学専攻": 1}, "author_org": {"1": ["長田 尚子"]}, "author": "長田 尚子", "abstract": null}, "65": {"url": "https://www.jstage.jst.go.jp/article/pjsai/JSAI03/0/JSAI03_0_65/_article/-char/ja", "title": "EMアルゴリズムを用いた教育支援のための自動生成解のエラー除去手法", "keywords": [], "co-author": ["小山 由紀江", "犬塚 信博"], "org": {"名古屋工業大学": 1}, "author_org": {"1": ["中野 智文", "小山 由紀江", "犬塚 信博"]}, "author": "中野 智文", "abstract": null}, "66": {"url": "https://www.jstage.jst.go.jp/article/pjsai/JSAI03/0/JSAI03_0_66/_article/-char/ja", "title": "教授戦略に基づいた学習コンテンツの系列化手法とその体系化", "keywords": [], "co-author": ["関 一也", "岡本 敏雄"], "org": {"電気通信大学　大学院情報システム学研究科": 1}, "author_org": {"1": ["松居 辰則", "関 一也", "岡本 敏雄"]}, "author": "松居 辰則", "abstract": null}, "67": {"url": "https://www.jstage.jst.go.jp/article/pjsai/JSAI03/0/JSAI03_0_67/_article/-char/ja", "title": "創造的協調場の構成支援へのオントロジー工学的アプローチ", "keywords": [], "co-author": ["小田原 理恵", "林 雄介", "池田 満", "溝口 理一郎"], "org": {"大阪大学産業科学研究所": 1, "北陸先端科学技術大学院大学": 2, "知識科学研究科": 3}, "author_org": {"1": ["武内 雅宇", "小田原 理恵", "林 雄介", "溝口 理一郎"], "2": ["池田 満"], "3": ["池田 満"]}, "author": "武内 雅宇", "abstract": null}, "68": {"url": "https://www.jstage.jst.go.jp/article/pjsai/JSAI03/0/JSAI03_0_68/_article/-char/ja", "title": "コミュニティウェブにおけるアクティブ情報検索ためのトピック抽出", "keywords": [], "co-author": ["石川 孝"], "org": {"日本工業大学": 1}, "author_org": {"1": ["余 東明", "石川 孝"]}, "author": "余 東明", "abstract": null}, "69": {"url": "https://www.jstage.jst.go.jp/article/pjsai/JSAI03/0/JSAI03_0_69/_article/-char/ja", "title": "Ｗｅｂからの人間関係ネットワークの抽出と情報支援", "keywords": [], "co-author": ["松尾 豊", "橋田 浩一", "石塚 満"], "org": {"産業技術総合研究所": 1, "科学技術振興事業団": 2, "東京大学": 3}, "author_org": {"1": ["松尾 豊", "橋田 浩一"], "2": ["松尾 豊", "橋田 浩一"], "3": ["友部 博教", "石塚 満"]}, "author": "友部 博教", "abstract": null}, "70": {"url": "https://www.jstage.jst.go.jp/article/pjsai/JSAI03/0/JSAI03_0_70/_article/-char/ja", "title": "Webコミュニティにおける中心性", "keywords": [], "co-author": [], "org": {"国立情報学研究所": 1, "科学技術振興事業団": 2}, "author_org": {"1": ["村田 剛志"], "2": ["村田 剛志"]}, "author": "村田 剛志", "abstract": null}, "71": {"url": "https://www.jstage.jst.go.jp/article/pjsai/JSAI03/0/JSAI03_0_71/_article/-char/ja", "title": "Webページの部分表示によるPDAへのWeb適応", "keywords": [], "co-author": ["山田 誠二", "新田 克巳"], "org": {"東京工業大学大学院": 1, "国立情報学研究所": 2}, "author_org": {"1": ["山本 浩司", "新田 克巳"], "2": ["山田 誠二"]}, "author": "山本 浩司", "abstract": null}, "72": {"url": "https://www.jstage.jst.go.jp/article/pjsai/JSAI03/0/JSAI03_0_72/_article/-char/ja", "title": "HTMLテキストの重要文を用いた画像ラベリング手法", "keywords": [], "co-author": ["砂山 渡", "谷内田 正彦"], "org": {"大阪大学大学院基礎工学研究科": 1}, "author_org": {"1": ["相良 直樹", "砂山 渡", "谷内田 正彦"]}, "author": "相良 直樹", "abstract": null}, "73": {"url": "https://www.jstage.jst.go.jp/article/pjsai/JSAI03/0/JSAI03_0_73/_article/-char/ja", "title": "実世界画像自動分類のためのWeb画像マイニング", "keywords": [], "co-author": [], "org": {"電気通信大学": 1}, "author_org": {"1": ["柳井 啓司"]}, "author": "柳井 啓司", "abstract": null}, "74": {"url": "https://www.jstage.jst.go.jp/article/pjsai/JSAI03/0/JSAI03_0_74/_article/-char/ja", "title": "Web上の画像情報源発見に向けて", "keywords": [], "co-author": ["高間 康史", "Stejic Zoran", "廣田 薫"], "org": {"都立科学技術大学": 1, "東京工業大学": 2}, "author_org": {"1": ["重森 圭輔", "高間 康史"], "2": ["Stejic Zoran", "廣田 薫"]}, "author": "重森 圭輔", "abstract": null}, "75": {"url": "https://www.jstage.jst.go.jp/article/pjsai/JSAI03/0/JSAI03_0_75/_article/-char/ja", "title": "キー概念辞書を用いないテキストの自動分類", "keywords": [], "co-author": ["酢山 明弘"], "org": {"株式会社　東芝": 1}, "author_org": {"1": ["櫻井 茂明", "酢山 明弘"]}, "author": "櫻井 茂明", "abstract": null}, "76": {"url": "https://www.jstage.jst.go.jp/article/pjsai/JSAI03/0/JSAI03_0_76/_article/-char/ja", "title": "生物医学文献データベースを利用するデータマイニング", "keywords": [], "co-author": ["沼尾 正行"], "org": {"東京工業大学": 1}, "author_org": {"1": ["TRAN TUAN-NAM", "沼尾 正行"]}, "author": "TRAN TUAN-NAM", "abstract": null}, "77": {"url": "https://www.jstage.jst.go.jp/article/pjsai/JSAI03/0/JSAI03_0_77/_article/-char/ja", "title": "帰納論理プログラミングシステムを利用したテキストデータの特徴発見", "keywords": [], "co-author": ["嶋津 恵子", "門馬 敦仁", "山根 洋平", "古川 康一"], "org": {"富士ゼロックス(株)研究本部　ITメディア研究所": 1, "慶應義塾大学　大学院　政策メディア研究科": 2}, "author_org": {"1": ["嶋津 恵子", "門馬 敦仁", "山根 洋平", "桜井 哲志"], "2": ["古川 康一"]}, "author": "桜井 哲志", "abstract": null}, "78": {"url": "https://www.jstage.jst.go.jp/article/pjsai/JSAI03/0/JSAI03_0_78/_article/-char/ja", "title": "エージェント技術を用いた複数データベースからのデータマイニング", "keywords": [], "co-author": [], "org": {"公立はこだて未来大学": 1}, "author_org": {"1": ["新美 礼彦"]}, "author": "新美 礼彦", "abstract": null}, "79": {"url": "https://www.jstage.jst.go.jp/article/pjsai/JSAI03/0/JSAI03_0_79/_article/-char/ja", "title": "薬物活性クラス分類へのサポートベクターマシン（SVM）の応用", "keywords": [], "co-author": ["高橋 由雅"], "org": {"豊橋技術科学大学　工学部": 1}, "author_org": {"1": ["錦織 克美", "高橋 由雅"]}, "author": "錦織 克美", "abstract": null}, "80": {"url": "https://www.jstage.jst.go.jp/article/pjsai/JSAI03/0/JSAI03_0_80/_article/-char/ja", "title": "分類ルール獲得のための抽象化部品探索", "keywords": [], "co-author": ["原口 誠"], "org": {"北海道大学": 1, "大学院工学研究科": 2, "電子情報工学専攻": 3}, "author_org": {"1": ["大久保 好章", "原口 誠"], "2": ["大久保 好章", "原口 誠"], "3": ["大久保 好章", "原口 誠"]}, "author": "大久保 好章", "abstract": null}, "81": {"url": "https://www.jstage.jst.go.jp/article/pjsai/JSAI03/0/JSAI03_0_81/_article/-char/ja", "title": "回帰木を利用した人工衛星運用データの異常検出支援", "keywords": [], "co-author": ["小笠原 志朗", "矢入 健久", "石濱 直樹", "堀 浩一", "中須賀 真一"], "org": {"東京大学": 1, "宇宙開発事業団": 2}, "author_org": {"1": ["中津川 実", "小笠原 志朗", "矢入 健久", "堀 浩一", "中須賀 真一"], "2": ["石濱 直樹"]}, "author": "中津川 実", "abstract": null}, "82": {"url": "https://www.jstage.jst.go.jp/article/pjsai/JSAI03/0/JSAI03_0_82/_article/-char/ja", "title": "因子分析と属性選択の統合に基づくデータの前処理機構", "keywords": [], "co-author": ["小森 麻央", "斎藤 淳", "阿部 秀尚", "山口 高平"], "org": {"静岡大学情報学部情報学研究科": 1, "": 2}, "author_org": {"1": ["渡邉 悠司", "小森 麻央", "阿部 秀尚", "山口 高平"], "2": ["斎藤 淳"]}, "author": "渡邉 悠司", "abstract": null}, "83": {"url": "https://www.jstage.jst.go.jp/article/pjsai/JSAI03/0/JSAI03_0_83/_article/-char/ja", "title": "ILPを用いた時系列データからの知識発見", "keywords": [], "co-author": [], "org": {"東京工業大学": 1}, "author_org": {"1": ["佐藤 慶宜"]}, "author": "佐藤 慶宜", "abstract": null}, "84": {"url": "https://www.jstage.jst.go.jp/article/pjsai/JSAI03/0/JSAI03_0_84/_article/-char/ja", "title": "時系列決定木による分類学習", "keywords": [], "co-author": ["鈴木 英之進", "横井 英人", "高林 克日己"], "org": {"横浜国立大学": 1, "大学院工学研究院": 2, "千葉大学": 3, "医学部附属病院医療情報部": 4}, "author_org": {"1": ["山田  悠", "鈴木 英之進"], "2": ["山田  悠", "鈴木 英之進"], "3": ["横井 英人", "高林 克日己"], "4": ["横井 英人", "高林 克日己"]}, "author": "山田  悠", "abstract": null}, "85": {"url": "https://www.jstage.jst.go.jp/article/pjsai/JSAI03/0/JSAI03_0_85/_article/-char/ja", "title": "構成型メタ学習と選択型メタ学習の比較評価", "keywords": [], "co-author": ["山口 高平"], "org": {"静岡大学大学院理工学研究科": 1, "静岡大学情報学部": 2}, "author_org": {"1": ["阿部 秀尚"], "2": ["山口 高平"]}, "author": "阿部 秀尚", "abstract": null}, "86": {"url": "https://www.jstage.jst.go.jp/article/pjsai/JSAI03/0/JSAI03_0_86/_article/-char/ja", "title": "オンラインコミュニティに基づく情報の社会的要約", "keywords": [], "co-author": ["片桐 恭弘"], "org": {"ATRメディア情報科学研究所": 1}, "author_org": {"1": ["高橋 徹", "片桐 恭弘"]}, "author": "高橋 徹", "abstract": null}, "87": {"url": "https://www.jstage.jst.go.jp/article/pjsai/JSAI03/0/JSAI03_0_87/_article/-char/ja", "title": "依存関係管理に基づく オントロジー分散構築支援システムの試作", "keywords": [], "co-author": [], "org": {"大阪大学": 1, "産業科学研究所": 2}, "author_org": {"1": ["砂川 英一"], "2": ["砂川 英一"]}, "author": "砂川 英一", "abstract": null}, "88": {"url": "https://www.jstage.jst.go.jp/article/pjsai/JSAI03/0/JSAI03_0_88/_article/-char/ja", "title": "知識チャンネルを用いた戦略的な知識流通手法", "keywords": [], "co-author": ["西田 豊明"], "org": {"東京大学工学系研究科": 1, "東京大学情報理工学系研究科": 2}, "author_org": {"1": ["久保田 秀和"], "2": ["西田 豊明"]}, "author": "久保田 秀和", "abstract": null}, "89": {"url": "https://www.jstage.jst.go.jp/article/pjsai/JSAI03/0/JSAI03_0_89/_article/-char/ja", "title": "ナノテクノロジー材料合成プロセスに関する機能的知識の体系的記述の試み", "keywords": [], "co-author": ["古崎 晃司", "來村 徳信", "渡邉 英一", "溝口 理一郎"], "org": {"大阪大学産業科学研究所": 1, "社団法人　化学工学会": 2}, "author_org": {"1": ["垂見 晋也", "古崎 晃司", "來村 徳信", "溝口 理一郎"], "2": ["渡邉 英一"]}, "author": "垂見 晋也", "abstract": null}, "90": {"url": "https://www.jstage.jst.go.jp/article/pjsai/JSAI03/0/JSAI03_0_90/_article/-char/ja", "title": "セマンティックWebのためのメタモデル管理ツール", "keywords": [], "co-author": ["和泉 憲明", "福田 直樹", "山口 高平"], "org": {"静岡大学大学院情報学研究科": 1, "産業技術総合研究所サイバーアシスト研究センター": 2, "静岡大学情報学部": 3}, "author_org": {"1": ["森田 武史"], "2": ["和泉 憲明"], "3": ["福田 直樹", "山口 高平"]}, "author": "森田 武史", "abstract": null}, "91": {"url": "https://www.jstage.jst.go.jp/article/pjsai/JSAI03/0/JSAI03_0_91/_article/-char/ja", "title": "Webサービス連携のための多粒度リポジトリ利用環境", "keywords": [], "co-author": ["和泉 憲明", "福田 直樹", "山口 高平"], "org": {"静岡大学大学院情報学研究科": 1, "産業技術総合研究所サイバーアシスト研究センター": 2, "静岡大学情報学部": 3}, "author_org": {"1": ["寺井 公一"], "2": ["和泉 憲明"], "3": ["福田 直樹", "山口 高平"]}, "author": "寺井 公一", "abstract": null}, "92": {"url": "https://www.jstage.jst.go.jp/article/pjsai/JSAI03/0/JSAI03_0_92/_article/-char/ja", "title": "JADEを用いたWebServices連携エージェントの設計と実装", "keywords": [], "co-author": ["和泉 憲明", "山口 高平"], "org": {"静岡大学情報学部": 1, "産業技術総合研究所サイバーアシスト研究センター": 2}, "author_org": {"1": ["福田 直樹", "山口 高平"], "2": ["和泉 憲明"]}, "author": "福田 直樹", "abstract": null}, "93": {"url": "https://www.jstage.jst.go.jp/article/pjsai/JSAI03/0/JSAI03_0_93/_article/-char/ja", "title": "問題解決のための知識マネージメントシステムの研究(第2報) - タスクの種類に応じた知識の記述 -", "keywords": [], "co-author": ["五十嵐 優", "社本 康広"], "org": {"北海道大学": 1, "清水建設": 2}, "author_org": {"1": ["吉岡 真治", "五十嵐 優"], "2": ["社本 康広"]}, "author": "吉岡 真治", "abstract": null}, "94": {"url": "https://www.jstage.jst.go.jp/article/pjsai/JSAI03/0/JSAI03_0_94/_article/-char/ja", "title": "インターネット上の情報／知識を扱う意思決定支援システム(DSIU)", "keywords": [], "co-author": ["山本 裕"], "org": {"有限会社フジモト・リサーチパーク": 1, "人工知能研究所": 2, "京都大学大学院": 3, "情報学研究科": 4, "複雑系科学専攻": 5}, "author_org": {"1": ["藤本 和則"], "2": ["藤本 和則"], "3": ["山本 裕"], "4": ["山本 裕"], "5": ["山本 裕"]}, "author": "藤本 和則", "abstract": null}, "95": {"url": "https://www.jstage.jst.go.jp/article/pjsai/JSAI03/0/JSAI03_0_95/_article/-char/ja", "title": "オープンソース・ソフトウェア開発を通した産学連携-イベント公開システムとNewsMLエディタ-", "keywords": [], "co-author": ["井上 明", "猪狩 淳一"], "org": {"甲南大学": 1, "毎日新聞社": 2, "同志社大学大学院": 3}, "author_org": {"1": ["井上 明"], "2": ["猪狩 淳一"], "3": ["金田 重郎"]}, "author": "金田 重郎", "abstract": null}, "96": {"url": "https://www.jstage.jst.go.jp/article/pjsai/JSAI03/0/JSAI03_0_96/_article/-char/ja", "title": "長岡技大テクノインキュベーションセンタが目指す課題解決型産学連携モデルとDSIUシステムへの期待", "keywords": [], "co-author": ["大重 稿二", "小田原 勝夫", "真野 淳", "岡崎 英人"], "org": {"長岡技術科学大学": 1, "ベアネット(株)": 2, "(社)TAMA産業活性化協会": 3}, "author_org": {"1": ["湯川 高志", "大重 稿二", "小田原 勝夫"], "2": ["真野 淳"], "3": ["岡崎 英人"]}, "author": "湯川 高志", "abstract": null}, "97": {"url": "https://www.jstage.jst.go.jp/article/pjsai/JSAI03/0/JSAI03_0_97/_article/-char/ja", "title": "ユーザ行動モデル構築のためのデータ解析システムの構想", "keywords": [], "co-author": ["中村 嘉志", "西村 拓一", "幸島 明男", "和泉 憲明", "松尾 豊"], "org": {"産業技術総合研究所　デジタルヒューマン研究センター": 1, "産業技術総合研究所　サイバーアシスト研究センター": 2}, "author_org": {"1": ["本村 陽一"], "2": ["中村 嘉志", "西村 拓一", "幸島 明男", "和泉 憲明", "松尾 豊"]}, "author": "本村 陽一", "abstract": null}, "98": {"url": "https://www.jstage.jst.go.jp/article/pjsai/JSAI03/0/JSAI03_0_98/_article/-char/ja", "title": "電子掲示板上の評判情報に基づく意思決定支援", "keywords": [], "co-author": ["松村 真宏", "岡崎 直観", "石塚 満"], "org": {"東京大学大学院情報理工学系研究科": 1}, "author_org": {"1": ["藤村 滋", "松村 真宏", "岡崎 直観", "石塚 満"]}, "author": "藤村 滋", "abstract": null}, "99": {"url": "https://www.jstage.jst.go.jp/article/pjsai/JSAI03/0/JSAI03_0_99/_article/-char/ja", "title": "意思決定のための探索過程の振りかえり支援 --- 探索履歴の空間配置 ---", "keywords": [], "co-author": ["白井 良成", "桑原 和宏"], "org": {"日本電信電話株式会社": 1, "ＮＴＴコミュニケーション科学基礎研究所": 2}, "author_org": {"1": ["松下 光範", "白井 良成", "桑原 和宏"], "2": ["松下 光範", "白井 良成", "桑原 和宏"]}, "author": "松下 光範", "abstract": null}, "100": {"url": "https://www.jstage.jst.go.jp/article/pjsai/JSAI03/0/JSAI03_0_100/_article/-char/ja", "title": "オンライン購買のための意思決定支援", "keywords": [], "co-author": ["堀 浩一"], "org": {"川村学園女子大学": 1, "東京大学": 2}, "author_org": {"1": ["庄司 裕子"], "2": ["堀 浩一"]}, "author": "庄司 裕子", "abstract": null}, "101": {"url": "https://www.jstage.jst.go.jp/article/pjsai/JSAI03/0/JSAI03_0_101/_article/-char/ja", "title": "観光コース作成支援に向けたイベント情報抽出とその組織化", "keywords": [], "co-author": ["内山 将夫", "山本 英子", "井佐原 均", "河野 恭之", "木戸出 正継"], "org": {"通信総合研究所": 1, "奈良先端科学技術大学院大学": 2}, "author_org": {"1": ["小作 浩美", "内山 将夫", "山本 英子", "井佐原 均"], "2": ["小作 浩美", "河野 恭之", "木戸出 正継"]}, "author": "小作 浩美", "abstract": null}, "102": {"url": "https://www.jstage.jst.go.jp/article/pjsai/JSAI03/0/JSAI03_0_102/_article/-char/ja", "title": "DSIUは“大きく社会貢献”できるか？：POCを例とした実用化の意義と限界", "keywords": [], "co-author": ["福原 知宏", "山下 耕二", "松村 憲一", "藤原 伸彦", "西田 豊明"], "org": {"北海道東海大学": 1, "通信総合研究所": 2, "鳴門教育大学": 3, "東京大学": 4}, "author_org": {"1": ["畦地 真太郎"], "2": ["福原 知宏", "山下 耕二", "松村 憲一"], "3": ["藤原 伸彦"], "4": ["西田 豊明"]}, "author": "畦地 真太郎", "abstract": null}, "103": {"url": "https://www.jstage.jst.go.jp/article/pjsai/JSAI03/0/JSAI03_0_103/_article/-char/ja", "title": "高齢者・障害者の自立的移動を支援するRobotic Communication Terminals - 要素システムの開発と統合", "keywords": [], "co-author": ["矢入（江口） 郁子", "猪木 誠二"], "org": {"通信総合研究所": 1}, "author_org": {"1": ["香山 健太郎", "矢入（江口） 郁子", "猪木 誠二"]}, "author": "香山 健太郎", "abstract": null}, "104": {"url": "https://www.jstage.jst.go.jp/article/pjsai/JSAI03/0/JSAI03_0_104/_article/-char/ja", "title": "歩行者支援を目的とした環境変動に頑強な道路状況の自動抽出", "keywords": [], "co-author": ["小村 剛史", "香山 健太郎", "吉水 宏"], "org": {"中部大学": 1, "通信総合研究所": 2}, "author_org": {"1": ["藤吉 弘亘", "小村 剛史"], "2": ["香山 健太郎", "吉水 宏"]}, "author": "藤吉 弘亘", "abstract": null}, "105": {"url": "https://www.jstage.jst.go.jp/article/pjsai/JSAI03/0/JSAI03_0_105/_article/-char/ja", "title": "視覚障害者の自立的移動を支援する携帯型情報通信端末の開発", "keywords": [], "co-author": ["香山 健太郎", "矢入(江口) 郁子", "西村 拓一", "猪木 誠二"], "org": {"通信総合研究所": 1, "産業技術総合研究所": 2}, "author_org": {"1": ["小山 慎哉", "香山 健太郎", "矢入(江口) 郁子", "猪木 誠二"], "2": ["西村 拓一"]}, "author": "小山 慎哉", "abstract": null}, "106": {"url": "https://www.jstage.jst.go.jp/article/pjsai/JSAI03/0/JSAI03_0_106/_article/-char/ja", "title": "無電源小型情報端末を用いたインタラクティブ情報支援", "keywords": [], "co-author": ["中村 嘉志", "伊藤 日出男", "山本 吉伸", "中島 秀之"], "org": {"産総研サイバーアシスト研究センター": 1, "CREST": 2}, "author_org": {"1": ["西村 拓一", "中村 嘉志", "伊藤 日出男", "山本 吉伸", "中島 秀之"], "2": ["西村 拓一", "伊藤 日出男", "山本 吉伸", "中島 秀之"]}, "author": "西村 拓一", "abstract": null}, "107": {"url": "https://www.jstage.jst.go.jp/article/pjsai/JSAI03/0/JSAI03_0_107/_article/-char/ja", "title": "重複障害者にも配慮できる移動支援のためのユーザー多様性の検討", "keywords": [], "co-author": ["矢入(江口) 郁子", "村井 佐知子", "五味 崇", "猪木 誠二"], "org": {"株式会社UFJ総合研究所": 1, "独立行政法人通信総合研究所": 2}, "author_org": {"1": ["柏野 聡彦", "村井 佐知子", "五味 崇"], "2": ["矢入(江口) 郁子", "猪木 誠二"]}, "author": "柏野 聡彦", "abstract": null}, "108": {"url": "https://www.jstage.jst.go.jp/article/pjsai/JSAI03/0/JSAI03_0_108/_article/-char/ja", "title": "ビークルのセンサー履歴データを用いた環境地図作成", "keywords": [], "co-author": [], "org": {"東京大学": 1}, "author_org": {"1": ["矢入 健久"]}, "author": "矢入 健久", "abstract": null}, "109": {"url": "https://www.jstage.jst.go.jp/article/pjsai/JSAI03/0/JSAI03_0_109/_article/-char/ja", "title": "歩行空間のアクセシビリティ情報を提供する移動支援GIS", "keywords": [], "co-author": ["吉岡 裕", "小松 正典", "猪木 誠二"], "org": {"独立行政法人　通信総合研究所": 1, "（株）ティージー情報ネットワーク": 2}, "author_org": {"1": ["矢入（江口） 郁子", "猪木 誠二"], "2": ["吉岡 裕", "小松 正典"]}, "author": "矢入（江口） 郁子", "abstract": null}, "110": {"url": "https://www.jstage.jst.go.jp/article/pjsai/JSAI03/0/JSAI03_0_110/_article/-char/ja", "title": "時系列マルチセンサ情報を用いた体験映像のセグメンテーション", "keywords": [], "co-author": ["河村 竜幸", "河野 恭之", "木戸出 正継"], "org": {"奈良先端科学技術大学院大学　情報科学研究科": 1}, "author_org": {"1": ["村田 賢", "河村 竜幸", "河野 恭之", "木戸出 正継"]}, "author": "村田 賢", "abstract": null}, "111": {"url": "https://www.jstage.jst.go.jp/article/pjsai/JSAI03/0/JSAI03_0_111/_article/-char/ja", "title": "テキスト情報からの制約に基づく料理画像中の物体検出", "keywords": [], "co-author": ["三浦 宏一", "浜田 玲子", "井手 一郎", "坂井 修一", "田中 英彦"], "org": {"東京大学工学部": 1, "東京大学大学院情報理工学系研究科": 2, "東京大学大学院工学系研究科": 3, "国立情報学研究所": 4}, "author_org": {"1": ["高野 求"], "2": ["三浦 宏一", "坂井 修一", "田中 英彦"], "3": ["浜田 玲子"], "4": ["井手 一郎"]}, "author": "高野 求", "abstract": null}, "112": {"url": "https://www.jstage.jst.go.jp/article/pjsai/JSAI03/0/JSAI03_0_112/_article/-char/ja", "title": "要約済異種メディアを利用した要約映像作成における規則の抽出", "keywords": [], "co-author": [], "org": {"早稲田大学理工学部白井研究室": 1}, "author_org": {"1": ["平林 衛"]}, "author": "平林 衛", "abstract": null}, "113": {"url": "https://www.jstage.jst.go.jp/article/pjsai/JSAI03/0/JSAI03_0_113/_article/-char/ja", "title": "A Framework for interactive Video-based Explanatory System", "keywords": [], "co-author": ["黒橋 禎夫", "西田 豊明"], "org": {"東京大学大学院情報理工学系研究科": 1}, "author_org": {"1": ["アヌチキッティクン ブリン", "黒橋 禎夫", "西田 豊明"]}, "author": "アヌチキッティクン ブリン", "abstract": null}, "114": {"url": "https://www.jstage.jst.go.jp/article/pjsai/JSAI03/0/JSAI03_0_114/_article/-char/ja", "title": "フレームを用いたVoiceXMLにおける対話制御", "keywords": [], "co-author": ["秋田 祥史"], "org": {"京都工芸繊維大学": 1}, "author_org": {"1": ["荒木 雅弘", "秋田 祥史"]}, "author": "荒木 雅弘", "abstract": null}, "115": {"url": "https://www.jstage.jst.go.jp/article/pjsai/JSAI03/0/JSAI03_0_115/_article/-char/ja", "title": "音声対話型コミュニケーション放送システムの開発", "keywords": [], "co-author": ["米澤 恵", "平野 義明"], "org": {"日立製作所中央研究所": 1, "日立製作所ビジネスソリューション事業部": 2, "日立製作所産業・流通システム事業部": 3}, "author_org": {"1": ["鯨井 俊宏"], "2": ["米澤 恵"], "3": ["平野 義明"]}, "author": "鯨井 俊宏", "abstract": null}, "116": {"url": "https://www.jstage.jst.go.jp/article/pjsai/JSAI03/0/JSAI03_0_116/_article/-char/ja", "title": "京都市バス運行情報案内システムの試験評価とユーザモデルの導入", "keywords": [], "co-author": ["駒谷 和範", "河原 達也", "奥乃 博"], "org": {"京都大学": 1}, "author_org": {"1": ["上野 晋一", "駒谷 和範", "河原 達也", "奥乃 博"]}, "author": "上野 晋一", "abstract": null}, "117": {"url": "https://www.jstage.jst.go.jp/article/pjsai/JSAI03/0/JSAI03_0_117/_article/-char/ja", "title": "擬人化エージェントGalateaのためのVoiceXML処理系", "keywords": [], "co-author": ["嵯峨山 茂樹"], "org": {"東京大学大学院": 1}, "author_org": {"1": ["西本 卓也", "嵯峨山 茂樹"]}, "author": "西本 卓也", "abstract": null}, "118": {"url": "https://www.jstage.jst.go.jp/article/pjsai/JSAI03/0/JSAI03_0_118/_article/-char/ja", "title": "汎用検索手法の２次元データへの拡張", "keywords": [], "co-author": ["足立 史宜", "鷲尾 隆", "元田 浩", "丹羽 雄二", "花房 英光"], "org": {"大阪大学産業科学研究所(I.S.I.R.,": 1, "Osaka": 2, "University)": 3, "_(株)_原子力安全システム研究所(INSS": 4, "Inc.)": 5}, "author_org": {"1": ["藤本 敦", "足立 史宜", "鷲尾 隆", "元田 浩"], "2": ["藤本 敦", "足立 史宜", "鷲尾 隆", "元田 浩"], "3": ["藤本 敦", "足立 史宜", "鷲尾 隆", "元田 浩"], "4": ["丹羽 雄二", "花房 英光"], "5": ["丹羽 雄二", "花房 英光"]}, "author": "藤本 敦", "abstract": null}, "119": {"url": "https://www.jstage.jst.go.jp/article/pjsai/JSAI03/0/JSAI03_0_119/_article/-char/ja", "title": "汎用検索手法の高速化と実適用", "keywords": [], "co-author": ["鷲尾 隆", "藤本 敦", "元田 浩", "丹羽 雄二", "花房 英光"], "org": {"大阪大学産業科学研究所": 1, "（株）原子力安全システム研究所": 2}, "author_org": {"1": ["足立 史宜", "鷲尾 隆", "藤本 敦", "元田 浩"], "2": ["丹羽 雄二", "花房 英光"]}, "author": "足立 史宜", "abstract": null}, "120": {"url": "https://www.jstage.jst.go.jp/article/pjsai/JSAI03/0/JSAI03_0_120/_article/-char/ja", "title": "基本動作制御モデル構築の為の歩行動作の分析及び生成", "keywords": [], "co-author": [], "org": {"早稲田大学白井研究室": 1}, "author_org": {"1": ["森野 岳宏"]}, "author": "森野 岳宏", "abstract": null}, "121": {"url": "https://www.jstage.jst.go.jp/article/pjsai/JSAI03/0/JSAI03_0_121/_article/-char/ja", "title": "モーションキャプチャデータを用いた歩行動作の分析と制御", "keywords": [], "co-author": [], "org": {"早稲田大学理工学部情報学科": 1}, "author_org": {"1": ["長船 大毅"]}, "author": "長船 大毅", "abstract": null}, "122": {"url": "https://www.jstage.jst.go.jp/article/pjsai/JSAI03/0/JSAI03_0_122/_article/-char/ja", "title": "知能ロボットの自律移動のための実画像からの物体認識", "keywords": [], "co-author": ["林 清鎮", "渡部 広一", "河岡 司"], "org": {"同志社大学": 1}, "author_org": {"1": ["樋口 雄一", "林 清鎮", "渡部 広一", "河岡 司"]}, "author": "樋口 雄一", "abstract": null}, "123": {"url": "https://www.jstage.jst.go.jp/article/pjsai/JSAI03/0/JSAI03_0_123/_article/-char/ja", "title": "知能ロボットの自律移動における経路地図作成", "keywords": [], "co-author": ["河岡 司", "渡部 広一"], "org": {"同志社大学工学部知識工学科知識情報処理研究室": 1, "": 2}, "author_org": {"1": ["田中 薫", "河岡 司"], "2": ["渡部 広一"]}, "author": "田中 薫", "abstract": null}, "124": {"url": "https://www.jstage.jst.go.jp/article/pjsai/JSAI03/0/JSAI03_0_124/_article/-char/ja", "title": "箏曲の歌における旋律パターンの分析と応用", "keywords": [], "co-author": ["白井 克彦"], "org": {"攻玉社工科短期大学": 1, "早稲田大学": 2}, "author_org": {"1": ["出口 幸子"], "2": ["白井 克彦"]}, "author": "出口 幸子", "abstract": null}, "125": {"url": "https://www.jstage.jst.go.jp/article/pjsai/JSAI03/0/JSAI03_0_125/_article/-char/ja", "title": "ユーザの適応を促す相互適応的インターフェイスシステム", "keywords": [], "co-author": ["宇都宮 淳", "鈴木 健太郎", "植田 一博", "開 一夫", "岡 夏樹"], "org": {"東京大学　大学院総合文化研究科": 1, "松下電器産業（株）": 2}, "author_org": {"1": ["小松 孝徳", "宇都宮 淳", "鈴木 健太郎", "植田 一博", "開 一夫"], "2": ["岡 夏樹"]}, "author": "小松 孝徳", "abstract": null}, "126": {"url": "https://www.jstage.jst.go.jp/article/pjsai/JSAI03/0/JSAI03_0_126/_article/-char/ja", "title": "人間とエージェントの相互適応", "keywords": [], "co-author": ["山口 智浩"], "org": {"国立情報学研究所": 1, "奈良工業高等専門学校": 2}, "author_org": {"1": ["山田 誠二"], "2": ["山口 智浩"]}, "author": "山田 誠二", "abstract": null}, "127": {"url": "https://www.jstage.jst.go.jp/article/pjsai/JSAI03/0/JSAI03_0_127/_article/-char/ja", "title": "擬人化エージェント同士の対話における視覚的ノンバーバル表現の制御", "keywords": [], "co-author": ["角所 考", "美濃 導彦"], "org": {"京都大学大学院情報学研究科": 1, "京都大学学術情報メディアセンター": 2}, "author_org": {"1": ["伊藤 淳子"], "2": ["角所 考", "美濃 導彦"]}, "author": "伊藤 淳子", "abstract": null}, "128": {"url": "https://www.jstage.jst.go.jp/article/pjsai/JSAI03/0/JSAI03_0_128/_article/-char/ja", "title": "確率モデルを用いた擬人化エージェントの表情表出", "keywords": [], "co-author": ["安村 禎明", "新田 克己"], "org": {"東京工業大学": 1}, "author_org": {"1": ["湯浅 将英", "安村 禎明", "新田 克己"]}, "author": "湯浅 将英", "abstract": null}, "129": {"url": "https://www.jstage.jst.go.jp/article/pjsai/JSAI03/0/JSAI03_0_129/_article/-char/ja", "title": "Infant Agents 間の対話による概念獲得と対話戦略", "keywords": [], "co-author": ["山本 航", "桂田 浩一", "新田 恒雄"], "org": {"豊橋技術大学": 1, "大学院工学研究科": 2}, "author_org": {"1": ["田口 亮", "山本 航", "桂田 浩一", "新田 恒雄"], "2": ["田口 亮", "山本 航", "桂田 浩一", "新田 恒雄"]}, "author": "田口 亮", "abstract": null}, "130": {"url": "https://www.jstage.jst.go.jp/article/pjsai/JSAI03/0/JSAI03_0_130/_article/-char/ja", "title": "ネットワーク端末としてのロボットデザインの意義と可能性（仮）", "keywords": [], "co-author": [""], "org": {"": 1, "著者所属：T-D-F": 2}, "author_org": {"1": ["園山 隆輔"], "2": [""]}, "author": "園山 隆輔", "abstract": null}, "131": {"url": "https://www.jstage.jst.go.jp/article/pjsai/JSAI03/0/JSAI03_0_131/_article/-char/ja", "title": "暗黙的コミュニケーション能力を有する自律移動椅子の評価", "keywords": [], "co-author": ["伊藤 昭"], "org": {"岐阜大学": 1}, "author_org": {"1": ["寺田 和憲", "伊藤 昭"]}, "author": "寺田 和憲", "abstract": null}, "132": {"url": "https://www.jstage.jst.go.jp/article/pjsai/JSAI03/0/JSAI03_0_132/_article/-char/ja", "title": "インタラクションを考慮したロボットの内部表現システムの検討", "keywords": [], "co-author": ["近藤 敏之", "伊藤 宏司"], "org": {"東京工業大学": 1}, "author_org": {"1": ["若松 良久", "近藤 敏之", "伊藤 宏司"]}, "author": "若松 良久", "abstract": null}, "133": {"url": "https://www.jstage.jst.go.jp/article/pjsai/JSAI03/0/JSAI03_0_133/_article/-char/ja", "title": "権威付けによるヒューマンロボットインタラクション", "keywords": [], "co-author": ["村上 直隆", "山田 誠二"], "org": {"東京工業大学": 1, "国立情報学研究所": 2}, "author_org": {"1": ["村上 直隆", "片上 大輔"], "2": ["山田 誠二"]}, "author": "片上 大輔", "abstract": null}, "134": {"url": "https://www.jstage.jst.go.jp/article/pjsai/JSAI03/0/JSAI03_0_134/_article/-char/ja", "title": "拡張一般化注釈付き論理プログラムによる形式的議論フレームワーク", "keywords": [], "co-author": ["梅田 勇一", "澤村 一"], "org": {"新潟大学": 1, "大学院": 2, "自然科学研究科": 3, "工学部": 4, "情報工学科": 5}, "author_org": {"1": ["高橋 武久", "梅田 勇一", "澤村 一"], "2": ["高橋 武久", "梅田 勇一"], "3": ["高橋 武久", "梅田 勇一"], "4": ["澤村 一"], "5": ["澤村 一"]}, "author": "高橋 武久", "abstract": null}, "135": {"url": "https://www.jstage.jst.go.jp/article/pjsai/JSAI03/0/JSAI03_0_135/_article/-char/ja", "title": "準無矛盾論理に基づく議論フレームワーク", "keywords": [], "co-author": ["高橋 武久", "澤村 一"], "org": {"新潟大学大学院自然科学研究科": 1, "新潟大学工学部情報工学科": 2}, "author_org": {"1": ["梅田 勇一", "高橋 武久"], "2": ["澤村 一"]}, "author": "梅田 勇一", "abstract": null}, "136": {"url": "https://www.jstage.jst.go.jp/article/pjsai/JSAI03/0/JSAI03_0_136/_article/-char/ja", "title": "差異を議論の動因にする議論エージェントシステム", "keywords": [], "co-author": ["高橋 武久", "澤村 一"], "org": {"新潟大学大学院自然科学研究科": 1, "新潟大学工学部情報工学科": 2}, "author_org": {"1": ["西潟 拓未", "高橋 武久"], "2": ["澤村 一"]}, "author": "西潟 拓未", "abstract": null}, "137": {"url": "https://www.jstage.jst.go.jp/article/pjsai/JSAI03/0/JSAI03_0_137/_article/-char/ja", "title": "議論過程に理解のプロセスを取り入れた議論するエージェントシステム", "keywords": [], "co-author": ["沢村 一"], "org": {"新潟大学": 1, "大学院": 2, "自然科学研究科": 3, "工学部": 4, "情報工学科": 5}, "author_org": {"1": ["田中 賢", "沢村 一"], "2": ["田中 賢"], "3": ["田中 賢"], "4": ["沢村 一"], "5": ["沢村 一"]}, "author": "田中 賢", "abstract": null}, "138": {"url": "https://www.jstage.jst.go.jp/article/pjsai/JSAI03/0/JSAI03_0_138/_article/-char/ja", "title": "確率的因果モデルを用いたエージェントの議論に基づく交渉の提案", "keywords": [], "co-author": ["大囿 忠親", "新谷 虎松"], "org": {"名古屋工業大学大学院": 1, "工学研究科": 2, "名古屋工業大学": 3, "電気情報工学専攻": 4}, "author_org": {"1": ["服部 宏充"], "2": ["服部 宏充"], "3": ["大囿 忠親", "新谷 虎松"], "4": ["大囿 忠親", "新谷 虎松"]}, "author": "服部 宏充", "abstract": null}, "139": {"url": "https://www.jstage.jst.go.jp/article/pjsai/JSAI03/0/JSAI03_0_139/_article/-char/ja", "title": "スタックを用いた議論プロトコルの実現法と議論評価法に関する研究", "keywords": [], "co-author": ["澤村 一"], "org": {"新潟大学": 1, "大学院": 2, "自然科学研究科": 3, "工学部": 4, "情報工学科": 5}, "author_org": {"1": ["登坂 大悟", "澤村 一"], "2": ["登坂 大悟"], "3": ["登坂 大悟"], "4": ["澤村 一"], "5": ["澤村 一"]}, "author": "登坂 大悟", "abstract": null}, "140": {"url": "https://www.jstage.jst.go.jp/article/pjsai/JSAI03/0/JSAI03_0_140/_article/-char/ja", "title": "経験知のリサイクルシステムの提案", "keywords": [], "co-author": ["吉村 宏樹", "増市 博", "大熊 智子"], "org": {"富士ゼロックス(株)": 1}, "author_org": {"1": ["吉岡 健", "吉村 宏樹", "増市 博", "大熊 智子"]}, "author": "吉岡 健", "abstract": null}, "141": {"url": "https://www.jstage.jst.go.jp/article/pjsai/JSAI03/0/JSAI03_0_141/_article/-char/ja", "title": "イベント設計における知識獲得のための方法論と知識再構築支援システムに関する研究", "keywords": [], "co-author": [], "org": {"東京大学大学院工学系研究科": 1}, "author_org": {"1": ["網谷 重紀"]}, "author": "網谷 重紀", "abstract": null}, "142": {"url": "https://www.jstage.jst.go.jp/article/pjsai/JSAI03/0/JSAI03_0_142/_article/-char/ja", "title": "知の創造・継承のための組織知メモリと評判", "keywords": [], "co-author": ["池田 満", "溝口 理一郎"], "org": {"大阪大学産業科学研究所": 1}, "author_org": {"1": ["林 雄介", "池田 満", "溝口 理一郎"]}, "author": "林 雄介", "abstract": null}, "143": {"url": "https://www.jstage.jst.go.jp/article/pjsai/JSAI03/0/JSAI03_0_143/_article/-char/ja", "title": "連想検索を利用したローカル文書管理システムの構築", "keywords": [], "co-author": ["山口 亨", "高間 康史"], "org": {"都立科学技術大学": 1, "科学技術振興事業団": 2}, "author_org": {"1": ["傘木 英将", "山口 亨", "高間 康史"], "2": ["山口 亨", "高間 康史"]}, "author": "傘木 英将", "abstract": null}, "144": {"url": "https://www.jstage.jst.go.jp/article/pjsai/JSAI03/0/JSAI03_0_144/_article/-char/ja", "title": "ドキュメントスキーミング支援環境の構築とその評価", "keywords": [], "co-author": ["金井 貴", "國藤 進"], "org": {"北陸先端科学技術大学院大学": 1}, "author_org": {"1": ["羽山 徹彩", "金井 貴", "國藤 進"]}, "author": "羽山 徹彩", "abstract": null}, "145": {"url": "https://www.jstage.jst.go.jp/article/pjsai/JSAI03/0/JSAI03_0_145/_article/-char/ja", "title": "ランドマーク物体の同時可視性に基づく配置地図学習", "keywords": [], "co-author": ["堀 浩一"], "org": {"東京大学": 1}, "author_org": {"1": ["矢入 健久", "堀 浩一"]}, "author": "矢入 健久", "abstract": null}, "146": {"url": "https://www.jstage.jst.go.jp/article/pjsai/JSAI03/0/JSAI03_0_146/_article/-char/ja", "title": "ビークル操縦者意図認識のためのセンサ配置の考察", "keywords": [], "co-author": ["矢入（江口） 郁子", "永合 宣明", "矢入 健久"], "org": {"独立行政法人": 1, "通信総合研究所": 2, "（株）アジル": 3, "東京大学大学院工学系研究科": 4}, "author_org": {"1": ["矢入（江口） 郁子", "猪木 誠二"], "2": ["矢入（江口） 郁子", "猪木 誠二"], "3": ["永合 宣明"], "4": ["矢入 健久"]}, "author": "猪木 誠二", "abstract": null}, "147": {"url": "https://www.jstage.jst.go.jp/article/pjsai/JSAI03/0/JSAI03_0_147/_article/-char/ja", "title": "ロボットにおける基礎定位とその調整機構", "keywords": [], "co-author": [], "org": {"京都大学大学院情報学研究科": 1, "国際電気通信基礎技術研究所": 2}, "author_org": {"1": ["李 銘義"], "2": ["李 銘義"]}, "author": "李 銘義", "abstract": null}, "148": {"url": "https://www.jstage.jst.go.jp/article/pjsai/JSAI03/0/JSAI03_0_148/_article/-char/ja", "title": "読書時の眼球運動を利用した受講者観察システム", "keywords": [], "co-author": ["杉本 圭"], "org": {"愛媛大学": 1}, "author_org": {"1": ["中川 祐治", "杉本 圭"]}, "author": "中川 祐治", "abstract": null}, "149": {"url": "https://www.jstage.jst.go.jp/article/pjsai/JSAI03/0/JSAI03_0_149/_article/-char/ja", "title": "SDDSモデルにもとづいた小学校理科のCSCLカリキュラム", "keywords": [], "co-author": [""], "org": {"": 1, "著者所属：静岡大学教育学部": 2}, "author_org": {"1": ["大島 純"], "2": [""]}, "author": "大島 純", "abstract": null}, "150": {"url": "https://www.jstage.jst.go.jp/article/pjsai/JSAI03/0/JSAI03_0_150/_article/-char/ja", "title": "学習履歴のメタ認知に基づく学習支援", "keywords": [], "co-author": [], "org": {"名古屋大学": 1}, "author_org": {"1": ["三輪 和久"]}, "author": "三輪 和久", "abstract": null}, "151": {"url": "https://www.jstage.jst.go.jp/article/pjsai/JSAI03/0/JSAI03_0_151/_article/-char/ja", "title": "メタ認知を活性化する学習支援システム", "keywords": [], "co-author": [], "org": {"九州工業大学": 1}, "author_org": {"1": ["平嶋　 宗"]}, "author": "平嶋　 宗", "abstract": null}, "152": {"url": "https://www.jstage.jst.go.jp/article/pjsai/JSAI03/0/JSAI03_0_152/_article/-char/ja", "title": "ナレッジマネージメントと協調学習", "keywords": [], "co-author": [], "org": {"北陸先端科学技術大学院大学": 1}, "author_org": {"1": ["池田 満"]}, "author": "池田 満", "abstract": null}, "153": {"url": "https://www.jstage.jst.go.jp/article/pjsai/JSAI03/0/JSAI03_0_153/_article/-char/ja", "title": "時系列イベントデータからの行動パターン発見", "keywords": [], "co-author": ["櫻井 茂明"], "org": {"（株）東芝": 1, "研究開発センター": 2, "知識メディアラボラトリー": 3}, "author_org": {"1": ["植野 研", "櫻井 茂明"], "2": ["植野 研", "櫻井 茂明"], "3": ["植野 研", "櫻井 茂明"]}, "author": "植野 研", "abstract": null}, "154": {"url": "https://www.jstage.jst.go.jp/article/pjsai/JSAI03/0/JSAI03_0_154/_article/-char/ja", "title": "滞在時間を考慮した主要行動パターン抽出方法の検討", "keywords": [], "co-author": ["小磯 貴史", "今崎 直樹"], "org": {"(株)東芝　研究開発センター": 1}, "author_org": {"1": ["服部 可奈子", "小磯 貴史", "今崎 直樹"]}, "author": "服部 可奈子", "abstract": null}, "155": {"url": "https://www.jstage.jst.go.jp/article/pjsai/JSAI03/0/JSAI03_0_155/_article/-char/ja", "title": "パス経路の類型化に基づくサッカー試合記録データからの知識獲得", "keywords": [], "co-author": ["津本 周作"], "org": {"島根医科大学医学部医療情報学講座": 1}, "author_org": {"1": ["平野 章二", "津本 周作"]}, "author": "平野 章二", "abstract": null}, "156": {"url": "https://www.jstage.jst.go.jp/article/pjsai/JSAI03/0/JSAI03_0_156/_article/-char/ja", "title": "マルコフモデルに基づく時系列データからの知識発見", "keywords": [], "co-author": ["吉田 由紀子", "小林 健一", "太田 唯子"], "org": {"（株）富士通研究所": 1}, "author_org": {"1": ["湯上 伸弘", "吉田 由紀子", "小林 健一", "太田 唯子"]}, "author": "湯上 伸弘", "abstract": null}, "157": {"url": "https://www.jstage.jst.go.jp/article/pjsai/JSAI03/0/JSAI03_0_157/_article/-char/ja", "title": "Decision Tree - Graph-Based Inductionの探索能力改善", "keywords": [], "co-author": ["松田 喬", "吉田 哲也", "元田 浩", "鷲尾 隆"], "org": {"大阪大学産業科学研究所": 1}, "author_org": {"1": ["ジアムサクン ワロドム", "松田 喬", "吉田 哲也", "元田 浩", "鷲尾 隆"]}, "author": "ジアムサクン ワロドム", "abstract": null}, "158": {"url": "https://www.jstage.jst.go.jp/article/pjsai/JSAI03/0/JSAI03_0_158/_article/-char/ja", "title": "縮約可能変数つきタグ木パターンを用いた半構造データからの情報抽出", "keywords": [], "co-author": ["鈴木 祐介", "正代 隆義", "内田 智之", "高橋 健一", "上田 祐彰"], "org": {"広島市立大学情報科学部": 1, "九州大学大学院システム情報科学府・研究院": 2}, "author_org": {"1": ["宮原 哲浩", "内田 智之", "高橋 健一", "上田 祐彰"], "2": ["鈴木 祐介", "正代 隆義"]}, "author": "宮原 哲浩", "abstract": null}, "159": {"url": "https://www.jstage.jst.go.jp/article/pjsai/JSAI03/0/JSAI03_0_159/_article/-char/ja", "title": "TFSを用いた化学構造データマイニング", "keywords": [], "co-author": ["高橋 由雅"], "org": {"豊橋技術科学大学　工学部": 1}, "author_org": {"1": ["藤島 悟志", "高橋 由雅"]}, "author": "藤島 悟志", "abstract": null}, "160": {"url": "https://www.jstage.jst.go.jp/article/pjsai/JSAI03/0/JSAI03_0_160/_article/-char/ja", "title": "多次元データにおける相関性の抽出", "keywords": [], "co-author": ["矢口 博之", "市野 学"], "org": {"東京電機大学　理工学部　情報社会学科": 1}, "author_org": {"1": ["松本 文士", "矢口 博之", "市野 学"]}, "author": "松本 文士", "abstract": null}, "161": {"url": "https://www.jstage.jst.go.jp/article/pjsai/JSAI03/0/JSAI03_0_161/_article/-char/ja", "title": "グリッド環境のためのロバストなデータ共有システムの設計", "keywords": [], "co-author": ["平石 広典", "溝口 文雄"], "org": {"東京理科大学理工学部": 1}, "author_org": {"1": ["嶺 行伸", "平石 広典", "溝口 文雄"]}, "author": "嶺 行伸", "abstract": null}, "162": {"url": "https://www.jstage.jst.go.jp/article/pjsai/JSAI03/0/JSAI03_0_162/_article/-char/ja", "title": "複数モジュールを介した記号・イメージ表現の接続による機能的な意味を有する人工物の定義", "keywords": [], "co-author": ["上里 福美"], "org": {"東京工芸大学大学院": 1}, "author_org": {"1": ["加村 和範", "上里 福美"]}, "author": "加村 和範", "abstract": null}, "163": {"url": "https://www.jstage.jst.go.jp/article/pjsai/JSAI03/0/JSAI03_0_163/_article/-char/ja", "title": "Situation CalculusによるHybrid Systemの記述と推論", "keywords": [], "co-author": ["房岡 璋"], "org": {"立命館大学": 1}, "author_org": {"1": ["中村 勝則", "房岡 璋"]}, "author": "中村 勝則", "abstract": null}, "164": {"url": "https://www.jstage.jst.go.jp/article/pjsai/JSAI03/0/JSAI03_0_164/_article/-char/ja", "title": "Self-referenced consciousness", "keywords": [], "co-author": [], "org": {"東京大学": 1, "": 2, "工学研究科": 3}, "author_org": {"1": ["三宅 陽一郎"], "2": ["三宅 陽一郎"], "3": ["三宅 陽一郎"]}, "author": "三宅 陽一郎", "abstract": null}, "165": {"url": "https://www.jstage.jst.go.jp/article/pjsai/JSAI03/0/JSAI03_0_165/_article/-char/ja", "title": "MGTPを用いた故障診断手法の効率化", "keywords": [], "co-author": ["江口 律子", "古川 康一", "筒井 良夫", "五十嵐 創", "玉川 直世"], "org": {"慶應義塾大学": 1, "大学院": 2, "政策・メディア研究科": 3, "宇宙開発事業団": 4}, "author_org": {"1": ["尾崎 知伸", "江口 律子", "古川 康一", "五十嵐 創", "玉川 直世"], "2": ["尾崎 知伸", "江口 律子", "古川 康一", "五十嵐 創", "玉川 直世"], "3": ["尾崎 知伸", "江口 律子", "古川 康一", "五十嵐 創", "玉川 直世"], "4": ["筒井 良夫"]}, "author": "尾崎 知伸", "abstract": null}, "166": {"url": "https://www.jstage.jst.go.jp/article/pjsai/JSAI03/0/JSAI03_0_166/_article/-char/ja", "title": "ラグランジュの方法を用いたCSPの解法", "keywords": [], "co-author": ["永松 正博"], "org": {"九州工業大学": 1}, "author_org": {"1": ["中野 隆宏", "永松 正博"]}, "author": "中野 隆宏", "abstract": null}, "167": {"url": "https://www.jstage.jst.go.jp/article/pjsai/JSAI03/0/JSAI03_0_167/_article/-char/ja", "title": "連続領域を導入したファジィ制約充足問題の解法", "keywords": [], "co-author": ["栗原 正仁", "三田村 保"], "org": {"北海道大学": 1, "北海道工業大学": 2}, "author_org": {"1": ["須藤 康裕", "栗原 正仁"], "2": ["三田村 保"]}, "author": "須藤 康裕", "abstract": null}, "168": {"url": "https://www.jstage.jst.go.jp/article/pjsai/JSAI03/0/JSAI03_0_168/_article/-char/ja", "title": "学生ネットワーク構築実験支援対話システム", "keywords": [], "co-author": ["内田 尚和", "石井 敏章", "高木 朗", "中島 秀之", "伊東 幸宏", "八名 和夫"], "org": {"法政大学工学部": 1, "（株）CSK": 2, "産業技術総合研究所サイバーアシスト研究センター": 3, "静岡大学情報学部": 4}, "author_org": {"1": ["常盤 大樹", "内田 尚和", "石井 敏章", "八名 和夫"], "2": ["高木 朗"], "3": ["高木 朗"], "4": ["中島 秀之", "伊東 幸宏"]}, "author": "常盤 大樹", "abstract": null}, "169": {"url": "https://www.jstage.jst.go.jp/article/pjsai/JSAI03/0/JSAI03_0_169/_article/-char/ja", "title": "物語における持続の分析とその応用", "keywords": [], "co-author": ["小方 孝"], "org": {"山梨大学工学部": 1}, "author_org": {"1": ["梅原 識貴", "小方 孝"]}, "author": "梅原 識貴", "abstract": null}, "170": {"url": "https://www.jstage.jst.go.jp/article/pjsai/JSAI03/0/JSAI03_0_170/_article/-char/ja", "title": "マンガのナラトロジーとハイパーコミックへの応用", "keywords": [], "co-author": ["小方 孝"], "org": {"山梨大学大学院工学研究科": 1, "山梨大学工学部": 2}, "author_org": {"1": ["遠藤 泰弘"], "2": ["小方 孝"]}, "author": "遠藤 泰弘", "abstract": null}, "171": {"url": "https://www.jstage.jst.go.jp/article/pjsai/JSAI03/0/JSAI03_0_171/_article/-char/ja", "title": "物語言説論と音楽構造の変形", "keywords": [], "co-author": ["小方 孝"], "org": {"山梨大学大学院工学研究科": 1, "山梨大学工学部": 2}, "author_org": {"1": ["小林 史典"], "2": ["小方 孝"]}, "author": "小林 史典", "abstract": null}, "172": {"url": "https://www.jstage.jst.go.jp/article/pjsai/JSAI03/0/JSAI03_0_172/_article/-char/ja", "title": "物語における距離の計算機構の提案", "keywords": [], "co-author": ["小方 孝"], "org": {"山梨大学工学部": 1}, "author_org": {"1": ["山影 沙耶夏", "小方 孝"]}, "author": "山影 沙耶夏", "abstract": null}, "173": {"url": "https://www.jstage.jst.go.jp/article/pjsai/JSAI03/0/JSAI03_0_173/_article/-char/ja", "title": "物語-ブランド関係に注目したTVCFの分析とCFシナリオ生成", "keywords": [], "co-author": ["小方 孝"], "org": {"山梨大学工学部": 1}, "author_org": {"1": ["萱森 修", "小方 孝"]}, "author": "萱森 修", "abstract": null}, "174": {"url": "https://www.jstage.jst.go.jp/article/pjsai/JSAI03/0/JSAI03_0_174/_article/-char/ja", "title": "触って聞いて楽しむサウンドアニメーション", "keywords": [], "co-author": ["村松 泰起", "矢入 郁子", "楠 房子", "西村 拓一"], "org": {"多摩美術大学": 1, "産業技術総合研究所": 2}, "author_org": {"1": ["市原 梢", "村松 泰起", "楠 房子"], "2": ["矢入 郁子", "西村 拓一"]}, "author": "市原 梢", "abstract": null}, "175": {"url": "https://www.jstage.jst.go.jp/article/pjsai/JSAI03/0/JSAI03_0_175/_article/-char/ja", "title": "セミオティックベースを使った日常言語アプリケーションシステム", "keywords": [], "co-author": ["岩爪 道昭", "小林 一郎", "伊藤 紀子", "高橋 祐介", "岩下 志乃", "菅野 道夫"], "org": {"理化学研究所脳科学総合研究センター": 1, "法政大学経済学部": 2}, "author_org": {"1": ["杉本 徹", "岩爪 道昭", "小林 一郎", "伊藤 紀子", "高橋 祐介", "岩下 志乃", "菅野 道夫"], "2": ["小林 一郎"]}, "author": "杉本 徹", "abstract": null}, "176": {"url": "https://www.jstage.jst.go.jp/article/pjsai/JSAI03/0/JSAI03_0_176/_article/-char/ja", "title": "セミオティックベースを使ったテキスト処理アルゴリズム", "keywords": [], "co-author": ["杉本 徹", "高橋 祐介", "小林 一郎"], "org": {"理化学研究所　脳科学総合研究センター": 1, "法政大学　経済学部": 2}, "author_org": {"1": ["伊藤 紀子", "杉本 徹", "高橋 祐介", "小林 一郎"], "2": ["小林 一郎"]}, "author": "伊藤 紀子", "abstract": null}, "177": {"url": "https://www.jstage.jst.go.jp/article/pjsai/JSAI03/0/JSAI03_0_177/_article/-char/ja", "title": "自然言語を媒介としたソフトウェア制御のための意味マッチング方式の検討", "keywords": [], "co-author": ["小林 一郎", "高橋 祐介", "菅野 道夫"], "org": {"理化学研究所　脳科学総合研究センター": 1, "法政大学　経済学部": 2}, "author_org": {"1": ["岩爪 道昭", "小林 一郎", "高橋 祐介", "菅野 道夫"], "2": ["小林 一郎"]}, "author": "岩爪 道昭", "abstract": null}, "178": {"url": "https://www.jstage.jst.go.jp/article/pjsai/JSAI03/0/JSAI03_0_178/_article/-char/ja", "title": "日常言語によるヘルプ出力の個人化について", "keywords": [], "co-author": ["小林 一郎", "伊藤 紀子", "杉本 徹", "菅野 道夫"], "org": {"理化学研究所": 1, "法政大学": 2}, "author_org": {"1": ["岩下 志乃", "小林 一郎", "伊藤 紀子", "杉本 徹", "菅野 道夫"], "2": ["小林 一郎"]}, "author": "岩下 志乃", "abstract": null}, "179": {"url": "https://www.jstage.jst.go.jp/article/pjsai/JSAI03/0/JSAI03_0_179/_article/-char/ja", "title": "人工オントロジーとボディランゲージ", "keywords": [], "co-author": ["村上 洋"], "org": {"東京都立科学技術大学": 1, "科学技術振興事業団さきがけ研究２１": 2}, "author_org": {"1": ["山口 亨", "村上 洋"], "2": ["山口 亨"]}, "author": "山口 亨", "abstract": null}, "180": {"url": "https://www.jstage.jst.go.jp/article/pjsai/JSAI03/0/JSAI03_0_180/_article/-char/ja", "title": "対話文脈への意味の位置付けを用いた対話システムの構築", "keywords": [], "co-author": ["野口 靖浩", "鈴木 夕紀子", "伊藤 敏彦", "小西 達裕", "近藤 真", "高木 朗", "中島 秀之", "伊東 幸宏"], "org": {"静岡大学情報学部": 1, "（株）ＣＳＫ": 2, "産総研サイバーアシスト研究センター": 3}, "author_org": {"1": ["池ヶ谷 有希", "野口 靖浩", "鈴木 夕紀子", "伊藤 敏彦", "小西 達裕", "近藤 真", "伊東 幸宏"], "2": ["高木 朗"], "3": ["高木 朗", "中島 秀之"]}, "author": "池ヶ谷 有希", "abstract": null}, "181": {"url": "https://www.jstage.jst.go.jp/article/pjsai/JSAI03/0/JSAI03_0_181/_article/-char/ja", "title": "Push like Talking: 言語対話メタファと意図推論による知的インタフェース", "keywords": [], "co-author": ["八木 雅彦"], "org": {"長岡技術科学大学": 1}, "author_org": {"1": ["山田 耕一", "八木 雅彦"]}, "author": "山田 耕一", "abstract": null}, "182": {"url": "https://www.jstage.jst.go.jp/article/pjsai/JSAI03/0/JSAI03_0_182/_article/-char/ja", "title": "マルチエージェントカレンダーシステムによるイベント日程スケジューリングについて", "keywords": [], "co-author": ["大囿 忠親", "新谷 虎松"], "org": {"名古屋工業大学大学院工学研究科": 1, "名古屋工業大学工学部知能情報システム学科": 2}, "author_org": {"1": ["磯村 厚誌"], "2": ["大囿 忠親", "新谷 虎松"]}, "author": "磯村 厚誌", "abstract": null}, "183": {"url": "https://www.jstage.jst.go.jp/article/pjsai/JSAI03/0/JSAI03_0_183/_article/-char/ja", "title": "設計における創造性支援環境「ユニバーサル・アブダクション・スタジオ」の提案", "keywords": [], "co-author": ["坂井 宏充", "野間口 大", "吉岡 真治", "下村 芳樹", "冨山 哲男"], "org": {"国立情報学研究所": 1, "東京大学　人工物工学研究センター": 2, "北海道大学": 3, "デルフト工科大学": 4}, "author_org": {"1": ["武田 英明"], "2": ["坂井 宏充", "野間口 大", "下村 芳樹"], "3": ["吉岡 真治"], "4": ["冨山 哲男"]}, "author": "武田 英明", "abstract": null}, "184": {"url": "https://www.jstage.jst.go.jp/article/pjsai/JSAI03/0/JSAI03_0_184/_article/-char/ja", "title": "シミュレーションによるデマンドバスにおける有用性の考察　ー都市サイズによる有用性の変化ー", "keywords": [], "co-author": ["野田 五十樹", "太田 正幸", "篠田 孝祐"], "org": {"北陸先端科学技術大学院大学　知識科学研究科": 1, "産業技術総合研究所　サイバーアシスト研究センター": 2}, "author_org": {"1": ["平田 敏之", "野田 五十樹", "篠田 孝祐"], "2": ["野田 五十樹", "太田 正幸", "篠田 孝祐"]}, "author": "平田 敏之", "abstract": null}, "185": {"url": "https://www.jstage.jst.go.jp/article/pjsai/JSAI03/0/JSAI03_0_185/_article/-char/ja", "title": "関心抽出に基づく話題構築支援に関する研究", "keywords": [], "co-author": ["大澤 幸生"], "org": {"筑波大学大学院　ビジネス科学研究科": 1}, "author_org": {"1": ["吉村 宏樹", "大澤 幸生"]}, "author": "吉村 宏樹", "abstract": null}, "186": {"url": "https://www.jstage.jst.go.jp/article/pjsai/JSAI03/0/JSAI03_0_186/_article/-char/ja", "title": "研究支援システムPapitsにおける論文分類機構のための特徴選択", "keywords": [], "co-author": ["大囿 忠親", "新谷 虎松"], "org": {"名古屋工業大学大学院工学研究科": 1, "名古屋工業大学知能情報システム学科": 2}, "author_org": {"1": ["長谷川 友治"], "2": ["大囿 忠親", "新谷 虎松"]}, "author": "長谷川 友治", "abstract": null}, "187": {"url": "https://www.jstage.jst.go.jp/article/pjsai/JSAI03/0/JSAI03_0_187/_article/-char/ja", "title": "＜拡張＞物語言説論の構図", "keywords": [], "co-author": [], "org": {"山梨大学工学部": 1}, "author_org": {"1": ["小方 孝"]}, "author": "小方 孝", "abstract": null}, "188": {"url": "https://www.jstage.jst.go.jp/article/pjsai/JSAI03/0/JSAI03_0_188/_article/-char/ja", "title": "＜拡張＞物語言説論の諸側面", "keywords": [], "co-author": ["小方 孝"], "org": {"山梨大学工学部": 1}, "author_org": {"1": ["小方 孝", "山影 沙耶夏"]}, "author": "山影 沙耶夏", "abstract": null}, "189": {"url": "https://www.jstage.jst.go.jp/article/pjsai/JSAI03/0/JSAI03_0_189/_article/-char/ja", "title": "物語性を考慮した要約に基づく類似文書の汎化", "keywords": [], "co-author": ["吉岡 真治", "溝江 彰人", "四ッ谷 雅輝"], "org": {"北海道大学": 1, "大学院工学研究科": 2, "電子情報工学専攻": 3}, "author_org": {"1": ["原口 誠", "吉岡 真治", "溝江 彰人", "四ッ谷 雅輝"], "2": ["原口 誠", "吉岡 真治", "溝江 彰人", "四ッ谷 雅輝"], "3": ["原口 誠", "吉岡 真治", "溝江 彰人", "四ッ谷 雅輝"]}, "author": "原口 誠", "abstract": null}, "190": {"url": "https://www.jstage.jst.go.jp/article/pjsai/JSAI03/0/JSAI03_0_190/_article/-char/ja", "title": "言葉で考えるコンピュータの実現にむけて", "keywords": [], "co-author": [], "org": {"拓殖大学": 1}, "author_org": {"1": ["石川　 勉"]}, "author": "石川　 勉", "abstract": null}, "191": {"url": "https://www.jstage.jst.go.jp/article/pjsai/JSAI03/0/JSAI03_0_191/_article/-char/ja", "title": "並列認識と概念知識を用いた単語の音声認識率向上手法", "keywords": [], "co-author": ["目片 小百合", "渡部 広一", "河岡 司"], "org": {"同志社大学": 1}, "author_org": {"1": ["葛谷 紳", "目片 小百合", "渡部 広一", "河岡 司"]}, "author": "葛谷 紳", "abstract": null}, "192": {"url": "https://www.jstage.jst.go.jp/article/pjsai/JSAI03/0/JSAI03_0_192/_article/-char/ja", "title": "動作語に対する知能ロボットのアクション生成方式", "keywords": [], "co-author": ["葛谷 紳", "渡部 広一", "河岡 司"], "org": {"同志社大学": 1}, "author_org": {"1": ["津原 一成", "葛谷 紳", "渡部 広一", "河岡 司"]}, "author": "津原 一成", "abstract": null}, "193": {"url": "https://www.jstage.jst.go.jp/article/pjsai/JSAI03/0/JSAI03_0_193/_article/-char/ja", "title": "常識的知覚判断システムの構築", "keywords": [], "co-author": ["渡部 広一", "河岡 司"], "org": {"同志社大学": 1}, "author_org": {"1": ["米谷 彩", "渡部 広一", "河岡 司"]}, "author": "米谷 彩", "abstract": null}, "194": {"url": "https://www.jstage.jst.go.jp/article/pjsai/JSAI03/0/JSAI03_0_194/_article/-char/ja", "title": "隠喩理解における創発特徴の生成機構", "keywords": [], "co-author": ["内海 彰"], "org": {"電気通信大学大学院電気通信学研究科システム工学専攻": 1, "電気通信大学電気通信学部システム工学科": 2}, "author_org": {"1": ["桑原 雄"], "2": ["内海 彰"]}, "author": "桑原 雄", "abstract": null}, "195": {"url": "https://www.jstage.jst.go.jp/article/pjsai/JSAI03/0/JSAI03_0_195/_article/-char/ja", "title": "比喩によってどのように詩的効果が喚起されるか：比喩の鑑賞過程の認知モデルに向けて", "keywords": [], "co-author": [], "org": {"電気通信大学電気通信学部システム工学科": 1}, "author_org": {"1": ["内海 彰"]}, "author": "内海 彰", "abstract": null}, "196": {"url": "https://www.jstage.jst.go.jp/article/pjsai/JSAI03/0/JSAI03_0_196/_article/-char/ja", "title": "概念連想に基づく職種判断システムの構築", "keywords": [], "co-author": ["渡部 広一", "河岡 司"], "org": {"同志社大学": 1}, "author_org": {"1": ["大江 奈緒子", "渡部 広一", "河岡 司"]}, "author": "大江 奈緒子", "abstract": null}, "197": {"url": "https://www.jstage.jst.go.jp/article/pjsai/JSAI03/0/JSAI03_0_197/_article/-char/ja", "title": "Web検索における　動作を観点とした情報分類方法", "keywords": [], "co-author": ["渡部 広一", "河岡 司"], "org": {"同志社大学": 1}, "author_org": {"1": ["堀田 真次", "渡部 広一", "河岡 司"]}, "author": "堀田 真次", "abstract": null}, "198": {"url": "https://www.jstage.jst.go.jp/article/pjsai/JSAI03/0/JSAI03_0_198/_article/-char/ja", "title": "検索用知識と常識的判断システムによる知的データベース検索", "keywords": [], "co-author": ["京塚 浩史", "渡部 広一", "河岡 司"], "org": {"同志社大学": 1}, "author_org": {"1": ["権 東旭", "京塚 浩史", "渡部 広一", "河岡 司"]}, "author": "権 東旭", "abstract": null}, "199": {"url": "https://www.jstage.jst.go.jp/article/pjsai/JSAI03/0/JSAI03_0_199/_article/-char/ja", "title": "文学の構造要素による文学の生成と評価について", "keywords": [], "co-author": [""], "org": {"": 1, "著者所属：前玉川ｆ大学教授": 2}, "author_org": {"1": ["岩垣 守彦"], "2": [""]}, "author": "岩垣 守彦", "abstract": null}, "200": {"url": "https://www.jstage.jst.go.jp/article/pjsai/JSAI03/0/JSAI03_0_200/_article/-char/ja", "title": "ノンストーリー(NS)の映像の修辞と認知", "keywords": [], "co-author": [], "org": {"日本学術振興会": 1, "山梨大学": 2}, "author_org": {"1": ["金井 明人"], "2": ["金井 明人"]}, "author": "金井 明人", "abstract": null}, "201": {"url": "https://www.jstage.jst.go.jp/article/pjsai/JSAI03/0/JSAI03_0_201/_article/-char/ja", "title": "小説の表現形態に関するハイパーテキストを指標とした評価方法の検討", "keywords": [], "co-author": ["藤田 米春"], "org": {"県立長崎シーボルト大学国際情報学部": 1, "大分大学工学部": 2}, "author_org": {"1": ["森田 均"], "2": ["藤田 米春"]}, "author": "森田 均", "abstract": null}, "202": {"url": "https://www.jstage.jst.go.jp/article/pjsai/JSAI03/0/JSAI03_0_202/_article/-char/ja", "title": "概略推論を用いた質問応答システムにおけるゴール抽出法", "keywords": [], "co-author": ["石川 勉"], "org": {"拓殖大学": 1}, "author_org": {"1": ["佐藤 雅彦", "石川 勉"]}, "author": "佐藤 雅彦", "abstract": null}, "203": {"url": "https://www.jstage.jst.go.jp/article/pjsai/JSAI03/0/JSAI03_0_203/_article/-char/ja", "title": "質問応答における回答絞り込み手法の比較", "keywords": [], "co-author": [], "org": {"三重大学工学部": 1}, "author_org": {"1": ["日高 直哉"]}, "author": "日高 直哉", "abstract": null}, "204": {"url": "https://www.jstage.jst.go.jp/article/pjsai/JSAI03/0/JSAI03_0_204/_article/-char/ja", "title": "コーチのアドバイスによるマルチエージェント環境への動的適応", "keywords": [], "co-author": ["新田 克巳"], "org": {"東京工業大学": 1, "総合理工学研究科": 2, "知能システム科学専攻": 3}, "author_org": {"1": ["秋山 英久", "新田 克巳"], "2": ["秋山 英久", "新田 克巳"], "3": ["秋山 英久", "新田 克巳"]}, "author": "秋山 英久", "abstract": null}, "205": {"url": "https://www.jstage.jst.go.jp/article/pjsai/JSAI03/0/JSAI03_0_205/_article/-char/ja", "title": "複雑な環境におけるマルチエージェント協調方式の設計", "keywords": [], "co-author": ["西田 豊明"], "org": {"東京大学": 1, "大学院情報理工学系研究科": 2}, "author_org": {"1": ["大竹 麗央", "西田 豊明"], "2": ["大竹 麗央", "西田 豊明"]}, "author": "大竹 麗央", "abstract": null}, "206": {"url": "https://www.jstage.jst.go.jp/article/pjsai/JSAI03/0/JSAI03_0_206/_article/-char/ja", "title": "マルチエージェント技術を用いた共同作業システムの設計と実装", "keywords": [], "co-author": ["西山 裕之", "平山 広典", "溝口 文雄"], "org": {"東京理科大学": 1}, "author_org": {"1": ["山崎 航", "西山 裕之", "平山 広典", "溝口 文雄"]}, "author": "山崎 航", "abstract": null}, "207": {"url": "https://www.jstage.jst.go.jp/article/pjsai/JSAI03/0/JSAI03_0_207/_article/-char/ja", "title": "HMM による協調動作の模倣学習", "keywords": [], "co-author": [], "org": {"産業技術総合研究所": 1, "科学技術振興事業団": 2, "北陸先端科学技術大学院大学": 3}, "author_org": {"1": ["野田 五十樹"], "2": ["野田 五十樹"], "3": ["野田 五十樹"]}, "author": "野田 五十樹", "abstract": null}, "208": {"url": "https://www.jstage.jst.go.jp/article/pjsai/JSAI03/0/JSAI03_0_208/_article/-char/ja", "title": "「相手を読む」戦略の獲得_-_標準問題の提案", "keywords": [], "co-author": ["水野 将史", "後藤 強", "寺田 和憲"], "org": {"岐阜大学工学部": 1}, "author_org": {"1": ["伊藤 昭", "水野 将史", "後藤 強", "寺田 和憲"]}, "author": "伊藤 昭", "abstract": null}, "209": {"url": "https://www.jstage.jst.go.jp/article/pjsai/JSAI03/0/JSAI03_0_209/_article/-char/ja", "title": "人間-エージェント間での読心ゲームにおける言い当て行動系列に依存したユーザモデルの推定", "keywords": [], "co-author": ["上利 宗久", "山田 誠二"], "org": {"国立奈良工業高等専門学校": 1, "国立情報学研究所": 2}, "author_org": {"1": ["山口 智浩", "上利 宗久"], "2": ["山田 誠二"]}, "author": "山口 智浩", "abstract": null}, "210": {"url": "https://www.jstage.jst.go.jp/article/pjsai/JSAI03/0/JSAI03_0_210/_article/-char/ja", "title": "Gestures realization for Embodied Conversational Agents", "keywords": [], "co-author": ["中野 有紀子", "西田 豊明"], "org": {"東京大学情報理工研究科": 1, "社会技術研究システム": 2}, "author_org": {"1": ["李 清", "西田 豊明"], "2": ["中野 有紀子"]}, "author": "李 清", "abstract": null}, "211": {"url": "https://www.jstage.jst.go.jp/article/pjsai/JSAI03/0/JSAI03_0_211/_article/-char/ja", "title": "スマートアシストを実現するセンサ系エージェント間協調システムの設計", "keywords": [], "co-author": ["溝口 文雄"], "org": {"東京理科大学理工学部": 1}, "author_org": {"1": ["西山 裕之", "溝口 文雄"]}, "author": "西山 裕之", "abstract": null}, "212": {"url": "https://www.jstage.jst.go.jp/article/pjsai/JSAI03/0/JSAI03_0_212/_article/-char/ja", "title": "カメラロボットの協調動作による人物追跡システムの設計", "keywords": [], "co-author": ["西山 裕之", "溝口 文雄"], "org": {"東京理科大学理工学部": 1}, "author_org": {"1": ["高橋 正樹", "西山 裕之", "溝口 文雄"]}, "author": "高橋 正樹", "abstract": null}, "213": {"url": "https://www.jstage.jst.go.jp/article/pjsai/JSAI03/0/JSAI03_0_213/_article/-char/ja", "title": "ベイジアンネットワークを用いたチェロ演奏スキルのモデル化の試み", "keywords": [], "co-author": ["植野 研", "森田 想平", "尾崎 知伸", "古川 康一"], "org": {"慶應義塾大学大学院政策・メディア研究科": 1, "慶應義塾大学SFC研究所": 2}, "author_org": {"1": ["五十嵐 創", "森田 想平", "尾崎 知伸", "古川 康一"], "2": ["植野 研"]}, "author": "五十嵐 創", "abstract": null}, "214": {"url": "https://www.jstage.jst.go.jp/article/pjsai/JSAI03/0/JSAI03_0_214/_article/-char/ja", "title": "モーションキャプチャを利用したダンサーの身体感覚の可視化の試み", "keywords": [], "co-author": ["五十嵐 創", "古川 康一"], "org": {"慶應義塾大学大学院": 1, "政策・メディア研究科": 2}, "author_org": {"1": ["森田 想平", "五十嵐 創", "古川 康一"], "2": ["森田 想平", "五十嵐 創", "古川 康一"]}, "author": "森田 想平", "abstract": null}, "215": {"url": "https://www.jstage.jst.go.jp/article/pjsai/JSAI03/0/JSAI03_0_215/_article/-char/ja", "title": "連続分布型HMMへの位相構造導入による全身運動を埋め込んだ原始シンボル空間構成法", "keywords": [], "co-author": ["稲邑 哲也", "中村 仁彦"], "org": {"東京大学大学院　情報理工学系研究科": 1}, "author_org": {"1": ["谷江 博昭", "稲邑 哲也", "中村 仁彦"]}, "author": "谷江 博昭", "abstract": null}, "216": {"url": "https://www.jstage.jst.go.jp/article/pjsai/JSAI03/0/JSAI03_0_216/_article/-char/ja", "title": "運動パターンの認識/生成の単一モデルとそれにもとづく離散的階層化による行動知能の集積", "keywords": [], "co-author": ["谷江 博昭", "中村 仁彦"], "org": {"東京大学大学院　情報理工学系研究科": 1}, "author_org": {"1": ["稲邑 哲也", "谷江 博昭", "中村 仁彦"]}, "author": "稲邑 哲也", "abstract": null}, "217": {"url": "https://www.jstage.jst.go.jp/article/pjsai/JSAI03/0/JSAI03_0_217/_article/-char/ja", "title": "身体知の解明を目指して", "keywords": [], "co-author": ["植野 研", "五十嵐 創", "森田 想平", "尾崎 知伸", "玉川 直世"], "org": {"慶應義塾大学大学院政策・メディア研究科": 1, "慶應義塾大学SFC研究所": 2}, "author_org": {"1": ["古川 康一", "森田 想平", "玉川 直世"], "2": ["植野 研", "五十嵐 創", "尾崎 知伸"]}, "author": "古川 康一", "abstract": null}, "218": {"url": "https://www.jstage.jst.go.jp/article/pjsai/JSAI03/0/JSAI03_0_218/_article/-char/ja", "title": "イベント空間情報支援プロジェクト", "keywords": [], "co-author": ["橋田 浩一", "中島 秀之"], "org": {"産総研サイバーアシスト研究センター": 1, "CREST": 2}, "author_org": {"1": ["西村 拓一", "橋田 浩一", "中島 秀之"], "2": ["西村 拓一", "橋田 浩一", "中島 秀之"]}, "author": "西村 拓一", "abstract": null}, "219": {"url": "https://www.jstage.jst.go.jp/article/pjsai/JSAI03/0/JSAI03_0_219/_article/-char/ja", "title": "イベント空間におけるインタラクションの支援から理解へ", "keywords": [], "co-author": [], "org": {"ATR情報科学研究所": 1}, "author_org": {"1": ["角 康之"]}, "author": "角 康之", "abstract": null}, "220": {"url": "https://www.jstage.jst.go.jp/article/pjsai/JSAI03/0/JSAI03_0_220/_article/-char/ja", "title": "イベント企画現場からの現状と夢", "keywords": [], "co-author": [], "org": {"株式会社　乃村工藝社": 1}, "author_org": {"1": ["岡 邦彦"]}, "author": "岡 邦彦", "abstract": null}, "221": {"url": "https://www.jstage.jst.go.jp/article/pjsai/JSAI03/0/JSAI03_0_221/_article/-char/ja", "title": "日常活動型ロボットRobovie開発の現状と将来展望", "keywords": [], "co-author": ["神田 崇行"], "org": {"ATR知能ロボティクス研究所": 1, "大阪大学工学研究科知能機能創成工学専攻": 2}, "author_org": {"1": ["石黒 浩", "神田 崇行"], "2": ["石黒 浩"]}, "author": "石黒 浩", "abstract": null}, "222": {"url": "https://www.jstage.jst.go.jp/article/pjsai/JSAI03/0/JSAI03_0_222/_article/-char/ja", "title": "イベント空間支援へのバリアフリーサービスモジュールの提案と移動支援への拡張", "keywords": [], "co-author": ["小山 慎哉", "西村 拓一", "猪木 誠二"], "org": {"独立行政法人　通信総合研究所": 1, "独立行政法人　産業技術総合研究所": 2}, "author_org": {"1": ["矢入（江口） 郁子", "小山 慎哉", "猪木 誠二"], "2": ["西村 拓一"]}, "author": "矢入（江口） 郁子", "abstract": null}, "223": {"url": "https://www.jstage.jst.go.jp/article/pjsai/JSAI03/0/JSAI03_0_223/_article/-char/ja", "title": "イベント空間におけるエデュテイメントを実現する情報支援", "keywords": [], "co-author": ["矢谷 浩司", "石川 葵", "石山 琢子", "山口 尚子", "西村 拓一", "杉本 雅則"], "org": {"多摩美術大学": 1, "東京大学": 2, "産業技術総合研究所": 3}, "author_org": {"1": ["楠 房子", "石川 葵", "石山 琢子", "山口 尚子"], "2": ["矢谷 浩司", "杉本 雅則"], "3": ["西村 拓一"]}, "author": "楠 房子", "abstract": null}, "224": {"url": "https://www.jstage.jst.go.jp/article/pjsai/JSAI03/0/JSAI03_0_224/_article/-char/ja", "title": "ウェアラブル側センサとインフラ側センサの協調とそのイベント空間情報支援への応用", "keywords": [], "co-author": ["興梠 正克", "西田 佳史", "中村 嘉志", "西村 拓一"], "org": {"産業技術総合研究所": 1}, "author_org": {"1": ["蔵田 武志", "興梠 正克", "西田 佳史", "中村 嘉志", "西村 拓一"]}, "author": "蔵田 武志", "abstract": null}, "225": {"url": "https://www.jstage.jst.go.jp/article/pjsai/JSAI03/0/JSAI03_0_225/_article/-char/ja", "title": "多視点カメラと方向制御ビーム光源による個別情報支援へ向けて", "keywords": [], "co-author": ["西村 拓一", "前川 仁"], "org": {"埼玉大学工学部": 1, "産総研サイバーアシスト研究センター": 2}, "author_org": {"1": ["岡谷(清水) 郁子", "前川 仁"], "2": ["西村 拓一"]}, "author": "岡谷(清水) 郁子", "abstract": null}, "226": {"url": "https://www.jstage.jst.go.jp/article/pjsai/JSAI03/0/JSAI03_0_226/_article/-char/ja", "title": "リフレッシュ型分散遺伝的アルゴリズム", "keywords": [], "co-author": ["三木 光範", "廣安 知之"], "org": {"同志社大学工学部": 1, "同志社大学大学院工学研究科": 2}, "author_org": {"1": ["三木 光範", "廣安 知之"], "2": ["勝崎 俊樹"]}, "author": "勝崎 俊樹", "abstract": null}, "227": {"url": "https://www.jstage.jst.go.jp/article/pjsai/JSAI03/0/JSAI03_0_227/_article/-char/ja", "title": "遺伝的アルゴリズムを用いた適応的近傍並列シミュレーテッドアニーリング", "keywords": [], "co-author": ["三木 光範", "廣安 知之"], "org": {"同志社大学工学部": 1, "同志社大学大学院工学研究科": 2}, "author_org": {"1": ["三木 光範", "廣安 知之"], "2": ["伏見 俊彦"]}, "author": "伏見 俊彦", "abstract": null}, "228": {"url": "https://www.jstage.jst.go.jp/article/pjsai/JSAI03/0/JSAI03_0_228/_article/-char/ja", "title": "遺伝的プログラミングにおける進化計算の高速化", "keywords": [], "co-author": [], "org": {"日本大学": 1}, "author_org": {"1": ["荒関 仁志"]}, "author": "荒関 仁志", "abstract": null}, "229": {"url": "https://www.jstage.jst.go.jp/article/pjsai/JSAI03/0/JSAI03_0_229/_article/-char/ja", "title": "遺伝的アルゴリズムによるルール変化型一次元セルオートマトンの進化", "keywords": [], "co-author": ["狩野 均"], "org": {"筑波大学システム情報工学研究科": 1, "筑波大学電子情報工学系": 2}, "author_org": {"1": ["烏 云"], "2": ["狩野 均"]}, "author": "烏 云", "abstract": null}, "230": {"url": "https://www.jstage.jst.go.jp/article/pjsai/JSAI03/0/JSAI03_0_230/_article/-char/ja", "title": "免疫系の抗体遺伝子組換え機構を取り入れた遺伝的アルゴリズムによる学習の性質", "keywords": [], "co-author": [], "org": {"富士ゼロックス(株)": 1}, "author_org": {"1": ["園田 隆志"]}, "author": "園田 隆志", "abstract": null}, "231": {"url": "https://www.jstage.jst.go.jp/article/pjsai/JSAI03/0/JSAI03_0_231/_article/-char/ja", "title": "遺伝的アルゴリズムによる自律移動ロボット用プログラムの進化", "keywords": [], "co-author": [], "org": {"金沢工業大学": 1}, "author_org": {"1": ["蜷川 繁"]}, "author": "蜷川 繁", "abstract": null}, "232": {"url": "https://www.jstage.jst.go.jp/article/pjsai/JSAI03/0/JSAI03_0_232/_article/-char/ja", "title": "順序のクラスタリング", "keywords": [], "co-author": [], "org": {"産業技術総合研究所": 1}, "author_org": {"1": ["神嶌 敏弘"]}, "author": "神嶌 敏弘", "abstract": null}, "233": {"url": "https://www.jstage.jst.go.jp/article/pjsai/JSAI03/0/JSAI03_0_233/_article/-char/ja", "title": "構造的類似性に基づくグラフクラスタリング", "keywords": [], "co-author": ["松田 喬", "吉田 哲也", "元田 浩", "鷲尾 隆"], "org": {"大阪大学産業科学研究所": 1}, "author_org": {"1": ["庄田 良介", "松田 喬", "吉田 哲也", "元田 浩", "鷲尾 隆"]}, "author": "庄田 良介", "abstract": null}, "234": {"url": "https://www.jstage.jst.go.jp/article/pjsai/JSAI03/0/JSAI03_0_234/_article/-char/ja", "title": "ウェブアクセスログのためのデータ圧縮に基づく逐次型部分空間クラスタリング", "keywords": [], "co-author": ["鈴木 英之進"], "org": {"横浜国立大学大学院工学研究院": 1}, "author_org": {"1": ["奈良橋 正樹", "鈴木 英之進"]}, "author": "奈良橋 正樹", "abstract": null}, "235": {"url": "https://www.jstage.jst.go.jp/article/pjsai/JSAI03/0/JSAI03_0_235/_article/-char/ja", "title": "状況分解が抽出する概念の性質についての考察", "keywords": [], "co-author": [], "org": {"(株)富士通研究所": 1}, "author_org": {"1": ["山川 宏"]}, "author": "山川 宏", "abstract": null}, "236": {"url": "https://www.jstage.jst.go.jp/article/pjsai/JSAI03/0/JSAI03_0_236/_article/-char/ja", "title": "帰納論理プログラミングにおける背景知識の能動的学習法", "keywords": [], "co-author": [], "org": {"東京理科大学　理工学部": 1}, "author_org": {"1": ["白井 秀範"]}, "author": "白井 秀範", "abstract": null}, "237": {"url": "https://www.jstage.jst.go.jp/article/pjsai/JSAI03/0/JSAI03_0_237/_article/-char/ja", "title": "大規模データマイニングのための頻出データアイテム発見アルゴリズムとネットワークデータへの応用", "keywords": [], "co-author": ["川副 真治", "浅井 達哉"], "org": {"九州大学大学院システム情報科学府": 1, "九州大学大学院システム情報科学研究院": 2}, "author_org": {"1": ["川副 真治", "浅井 達哉"], "2": ["有村 博紀"]}, "author": "有村 博紀", "abstract": null}, "238": {"url": "https://www.jstage.jst.go.jp/article/pjsai/JSAI03/0/JSAI03_0_238/_article/-char/ja", "title": "類似度に基づくVisual Data Mining - 近未来チャレンジ2002の評価シートへの適用 -", "keywords": [], "co-author": ["安田 晃", "笠原 要", "西浦  敬信", "額賀 信尾"], "org": {"島根医科大学医療情報学": 1, "日本電信電話(株)": 2, "NTT": 3, "コミュニケーション科学基礎研究所": 4, "ATR": 5, "音声言語通信研究所": 6, "日立製作所中央研究所": 7}, "author_org": {"1": ["津本 周作", "安田 晃"], "2": ["笠原 要"], "3": ["笠原 要"], "4": ["笠原 要"], "5": ["西浦  敬信"], "6": ["西浦  敬信"], "7": ["額賀 信尾"]}, "author": "津本 周作", "abstract": null}, "239": {"url": "https://www.jstage.jst.go.jp/article/pjsai/JSAI03/0/JSAI03_0_239/_article/-char/ja", "title": "類似関係にある複数カテゴリの組み合わせの発見", "keywords": [], "co-author": ["武田 英明"], "org": {"国立情報学研究所": 1}, "author_org": {"1": ["市瀬 龍太郎", "武田 英明"]}, "author": "市瀬 龍太郎", "abstract": null}, "240": {"url": "https://www.jstage.jst.go.jp/article/pjsai/JSAI03/0/JSAI03_0_240/_article/-char/ja", "title": "Profit Sharing法における強化関数に関する一考察", "keywords": [], "co-author": ["辰巳 昭治", "北村 泰彦"], "org": {"大阪市立大学大学院工学研究科": 1}, "author_org": {"1": ["植村 渉", "辰巳 昭治", "北村 泰彦"]}, "author": "植村 渉", "abstract": null}, "241": {"url": "https://www.jstage.jst.go.jp/article/pjsai/JSAI03/0/JSAI03_0_241/_article/-char/ja", "title": "罰を考慮したProfit Sharing強化学習法", "keywords": [], "co-author": [], "org": {"名古屋工業大学": 1}, "author_org": {"1": ["鈴木 淳司"]}, "author": "鈴木 淳司", "abstract": null}, "242": {"url": "https://www.jstage.jst.go.jp/article/pjsai/JSAI03/0/JSAI03_0_242/_article/-char/ja", "title": "POMDPsへの行動優先度学習型強化学習アルゴリズムの適用", "keywords": [], "co-author": ["犬塚 信博", "世木 博久"], "org": {"名古屋工業大学": 1}, "author_org": {"1": ["松井 藤五郎", "犬塚 信博", "世木 博久"]}, "author": "松井 藤五郎", "abstract": null}, "243": {"url": "https://www.jstage.jst.go.jp/article/pjsai/JSAI03/0/JSAI03_0_243/_article/-char/ja", "title": "コスト付きマルコフ決定過程における強化学習アルゴリズム", "keywords": [], "co-author": ["松井 藤五郎", "犬塚 信博", "和田 幸一"], "org": {"名古屋工業大学電気情報工学科": 1}, "author_org": {"1": ["石黒 誉久", "松井 藤五郎", "犬塚 信博", "和田 幸一"]}, "author": "石黒 誉久", "abstract": null}, "244": {"url": "https://www.jstage.jst.go.jp/article/pjsai/JSAI03/0/JSAI03_0_244/_article/-char/ja", "title": "非マルコフ性を有する環境のモデリング", "keywords": [], "co-author": ["栗原 正仁"], "org": {"北海道大学　大学院工学研究科　システム情報工学専攻": 1}, "author_org": {"1": ["金澤 勇樹", "栗原 正仁"]}, "author": "金澤 勇樹", "abstract": null}, "245": {"url": "https://www.jstage.jst.go.jp/article/pjsai/JSAI03/0/JSAI03_0_245/_article/-char/ja", "title": "各種のゲームで適切な行動を導く自己評価の生成法", "keywords": [], "co-author": ["沼尾 正行"], "org": {"東京工業大学": 1, "情報理工学研究科": 2, "計算工学専攻": 3}, "author_org": {"1": ["森山 甲一", "沼尾 正行"], "2": ["森山 甲一", "沼尾 正行"], "3": ["森山 甲一", "沼尾 正行"]}, "author": "森山 甲一", "abstract": null}, "246": {"url": "https://www.jstage.jst.go.jp/article/pjsai/JSAI03/0/JSAI03_0_246/_article/-char/ja", "title": "強化学習を用いたSoar情報収集機構の試作", "keywords": [], "co-author": ["大囿 忠親", "新谷 虎松"], "org": {"名古屋工業大学大学院工学研究科": 1, "名古屋工業大学工学部知能情報システム学科": 2}, "author_org": {"1": ["保知 良暢"], "2": ["大囿 忠親", "新谷 虎松"]}, "author": "保知 良暢", "abstract": null}, "247": {"url": "https://www.jstage.jst.go.jp/article/pjsai/JSAI03/0/JSAI03_0_247/_article/-char/ja", "title": "マクロアクションの自動生成について", "keywords": [], "co-author": [""], "org": {"": 1, "著者所属：京都大学情報学研究科": 2}, "author_org": {"1": ["陳 宇"], "2": [""]}, "author": "陳 宇", "abstract": null}, "248": {"url": "https://www.jstage.jst.go.jp/article/pjsai/JSAI03/0/JSAI03_0_248/_article/-char/ja", "title": "Prologによるゲームプレイヤーのモデリング", "keywords": [], "co-author": [], "org": {"関東学園大学": 1}, "author_org": {"1": ["犬童 健良"]}, "author": "犬童 健良", "abstract": null}, "249": {"url": "https://www.jstage.jst.go.jp/article/pjsai/JSAI03/0/JSAI03_0_249/_article/-char/ja", "title": "動作からのサービス技能共有", "keywords": [], "co-author": ["堀 聡", "広瀬 公太", "瀧 寛和"], "org": {"ものつくり大学": 1, "和歌山大学": 2}, "author_org": {"1": ["堀 聡", "杉本 誠", "広瀬 公太"], "2": ["瀧 寛和"]}, "author": "杉本 誠", "abstract": null}, "250": {"url": "https://www.jstage.jst.go.jp/article/pjsai/JSAI03/0/JSAI03_0_250/_article/-char/ja", "title": "POC Communicator: 話の作成・共有環境", "keywords": [], "co-author": ["西田 豊明"], "org": {"独立行政法人通信総合研究所けいはんな情報通信融合研究センター西田結集型特別グループ": 1, "東京大学大学院情報理工学系研究科": 2}, "author_org": {"1": ["福原 知宏", "西田 豊明"], "2": ["西田 豊明"]}, "author": "福原 知宏", "abstract": null}, "251": {"url": "https://www.jstage.jst.go.jp/article/pjsai/JSAI03/0/JSAI03_0_251/_article/-char/ja", "title": "高齢者・障害者を含む歩行者向け移動支援ＧＩＳ", "keywords": [], "co-author": ["吉岡 裕", "矢入（江口） 郁子", "猪木 誠二"], "org": {"株式会社ティージー情報ネットワーク": 1, "独立行政法人通信総合研究所": 2}, "author_org": {"1": ["小松 正典", "吉岡 裕"], "2": ["矢入（江口） 郁子", "猪木 誠二"]}, "author": "小松 正典", "abstract": null}, "252": {"url": "https://www.jstage.jst.go.jp/article/pjsai/JSAI03/0/JSAI03_0_252/_article/-char/ja", "title": "ネットワーク上を移動しながら知恵を授かるモバイルエージェント", "keywords": [], "co-author": ["梅田 勇一", "沢村 一"], "org": {"新潟大学大学院自然科学研究科": 1, "新潟大学工学部情報工学科": 2}, "author_org": {"1": ["川上 渉", "梅田 勇一"], "2": ["沢村 一"]}, "author": "川上 渉", "abstract": null}, "253": {"url": "https://www.jstage.jst.go.jp/article/pjsai/JSAI03/0/JSAI03_0_253/_article/-char/ja", "title": "携帯電話を用いた協調的タスクスケジューラ", "keywords": [], "co-author": ["武田 英明"], "org": {"総合研究大学院大学": 1, "国立情報学研究所": 2}, "author_org": {"1": ["大向 一輝", "武田 英明"], "2": ["武田 英明"]}, "author": "大向 一輝", "abstract": null}, "50": {"url": "https://www.jstage.jst.go.jp/article/pjsai/JSAI03/0/JSAI03_0_50/_article/-char/ja", "title": "ネットワーク・コミュニティを活性化する", "keywords": [], "co-author": ["畦地 真太郎", "山下 耕二", "福原 知宏"], "org": {"CRL": 1, "西田結集型特別グループ": 2, "大阪大学大学院人間科学研究科": 3, "北海道東海大学": 4}, "author_org": {"1": ["松村 憲一", "山下 耕二", "福原 知宏"], "2": ["松村 憲一", "山下 耕二", "福原 知宏"], "3": ["松村 憲一"], "4": ["畦地 真太郎"]}, "author": "松村 憲一", "abstract": null}, "51": {"url": "https://www.jstage.jst.go.jp/article/pjsai/JSAI03/0/JSAI03_0_51/_article/-char/ja", "title": "コミュニティ支援システムにおけるコミュニティ運営・分析支援機能", "keywords": [], "co-author": ["近間 正樹", "西田 豊明"], "org": {"独立行政法人通信総合研究所けいはんな情報通信融合研究センター西田結集型特別グループ": 1, "奈良先端科学技術大学院大学情報科学研究科": 2, "東京大学大学院情報理工学系研究科": 3}, "author_org": {"1": ["福原 知宏", "近間 正樹", "西田 豊明"], "2": ["福原 知宏", "近間 正樹"], "3": ["西田 豊明"]}, "author": "福原 知宏", "abstract": null}, "52": {"url": "https://www.jstage.jst.go.jp/article/pjsai/JSAI03/0/JSAI03_0_52/_article/-char/ja", "title": "コミュニティ交流活動モデルを基礎とした知の創造・継承支援環境", "keywords": [], "co-author": ["津本 紘享", "林 雄介", "池田 満", "溝口 理一郎"], "org": {"大阪大学産業科学研究所": 1}, "author_org": {"1": ["田中 庸平", "津本 紘享", "林 雄介", "池田 満", "溝口 理一郎"]}, "author": "田中 庸平", "abstract": null}, "53": {"url": "https://www.jstage.jst.go.jp/article/pjsai/JSAI03/0/JSAI03_0_53/_article/-char/ja", "title": "機能的設計知識記述・共有の枠組みとその実用展開", "keywords": [], "co-author": ["小路 悠介", "高橋 知伸", "吉川 真理子", "柏瀬 雅一", "布瀬 雅義", "溝口 理一郎"], "org": {"大阪大学　産業科学研究所": 1, "住友電気工業株式会社": 2}, "author_org": {"1": ["來村 徳信", "小路 悠介", "高橋 知伸", "吉川 真理子", "溝口 理一郎"], "2": ["柏瀬 雅一", "布瀬 雅義"]}, "author": "來村 徳信", "abstract": null}, "54": {"url": "https://www.jstage.jst.go.jp/article/pjsai/JSAI03/0/JSAI03_0_54/_article/-char/ja", "title": "機能モデルにおける補助機能の分類とその設計意図の明示化について", "keywords": [], "co-author": ["來村 徳信", "溝口 理一郎"], "org": {"大阪大学　産業科学研究所": 1}, "author_org": {"1": ["小路 悠介", "來村 徳信", "溝口 理一郎"]}, "author": "小路 悠介", "abstract": null}, "55": {"url": "https://www.jstage.jst.go.jp/article/pjsai/JSAI03/0/JSAI03_0_55/_article/-char/ja", "title": "携帯電話のコンテンツ利用に関する知識共有方式の検討", "keywords": [], "co-author": [], "org": {"NTTドコモ株式会社": 1}, "author_org": {"1": ["長沼 武史"]}, "author": "長沼 武史", "abstract": null}, "56": {"url": "https://www.jstage.jst.go.jp/article/pjsai/JSAI03/0/JSAI03_0_56/_article/-char/ja", "title": "記録間の関連付けによる助言の蓄積", "keywords": [], "co-author": ["松田 憲幸", "瀧 寛和", "安部 憲広", "堀 聡"], "org": {"和歌山大学システム工学部": 1, "九州工業大学": 2, "ものつくり大学": 3}, "author_org": {"1": ["原田 勝行", "松田 憲幸", "瀧 寛和"], "2": ["安部 憲広"], "3": ["堀 聡"]}, "author": "原田 勝行", "abstract": null}}